{
  "secCode": "4021",
  "issuerName": "日産化学株式会社",
  "updated_at": "2026/07/06 22:54 JST",
  "latestDate": "2026-06-24",
  "latest": [
    {
      "rank": 1,
      "name": "日本マスタートラスト信託銀行株式会社(信託口)",
      "shares": 33468000,
      "ratio": 24.93,
      "category": "trust",
      "category_label": "信託口（国内機関・年金/投信）",
      "is_founder_family": false
    },
    {
      "rank": 2,
      "name": "株式会社日本カストディ銀行（信託口）",
      "shares": 16114000,
      "ratio": 12.0,
      "category": "trust",
      "category_label": "信託口（国内機関・年金/投信）",
      "is_founder_family": false
    },
    {
      "rank": 3,
      "name": "みずほ信託銀行株式会社 退職給付信託 みずほ銀行口 再信託受託者 株式会社日本カストディ銀行",
      "shares": 5467000,
      "ratio": 4.07,
      "category": "trust",
      "category_label": "信託口（国内機関・年金/投信）",
      "is_founder_family": false
    },
    {
      "rank": 4,
      "name": "日産化学 取引先持株会",
      "shares": 3762000,
      "ratio": 2.8,
      "category": "employee",
      "category_label": "従業員持株会",
      "is_founder_family": false
    },
    {
      "rank": 5,
      "name": "STATE STREET BANK AND TRUST COMPANY 505103(常任代理人　株式会社みずほ銀行決済営業部)",
      "shares": 1878000,
      "ratio": 1.4,
      "category": "foreign",
      "category_label": "外国機関投資家",
      "is_founder_family": false
    },
    {
      "rank": 6,
      "name": "明治安田生命保険相互会社",
      "shares": 1861000,
      "ratio": 1.39,
      "category": "financial",
      "category_label": "銀行・保険",
      "is_founder_family": false
    },
    {
      "rank": 7,
      "name": "JP MORGAN CHASE BANK 385781(常任代理人　株式会社みずほ銀行決済営業部)",
      "shares": 1833000,
      "ratio": 1.37,
      "category": "foreign",
      "category_label": "外国機関投資家",
      "is_founder_family": false
    },
    {
      "rank": 8,
      "name": "STATE STREET BANK AND TRUST COMPANY 505001(常任代理人　株式会社みずほ銀行決済営業部)",
      "shares": 1807000,
      "ratio": 1.35,
      "category": "foreign",
      "category_label": "外国機関投資家",
      "is_founder_family": false
    },
    {
      "rank": 9,
      "name": "HSBC HONG KONG-TREASURY SERVICES A/C ASIAN EQUITIES DERIVATIVES(常任代理人　香港上海銀行東京支店セキュリティーズ・サービシズ・オペレーションズ)",
      "shares": 1726000,
      "ratio": 1.29,
      "category": "foreign",
      "category_label": "外国機関投資家",
      "is_founder_family": false
    },
    {
      "rank": 10,
      "name": "JPモルガン証券株式会社",
      "shares": 1685000,
      "ratio": 1.26,
      "category": "securities",
      "category_label": "証券会社",
      "is_founder_family": false
    }
  ],
  "latestSummary": {
    "by_category": {
      "trust": 41.0,
      "employee": 2.8,
      "foreign": 5.41,
      "financial": 1.39,
      "securities": 1.26
    },
    "individual_total": 0,
    "top10_total": 51.86
  },
  "history": [
    {
      "submitDate": "2026-06-24",
      "docType": "120",
      "docTypeName": "有価証券報告書－第156期(2025/04/01－2026/03/31)",
      "docID": "S100YIML",
      "shareholders": [
        {
          "rank": 1,
          "name": "日本マスタートラスト信託銀行株式会社(信託口)",
          "shares": 33468000,
          "ratio": 24.93,
          "category": "trust",
          "category_label": "信託口（国内機関・年金/投信）",
          "is_founder_family": false
        },
        {
          "rank": 2,
          "name": "株式会社日本カストディ銀行（信託口）",
          "shares": 16114000,
          "ratio": 12.0,
          "category": "trust",
          "category_label": "信託口（国内機関・年金/投信）",
          "is_founder_family": false
        },
        {
          "rank": 3,
          "name": "みずほ信託銀行株式会社 退職給付信託 みずほ銀行口 再信託受託者 株式会社日本カストディ銀行",
          "shares": 5467000,
          "ratio": 4.07,
          "category": "trust",
          "category_label": "信託口（国内機関・年金/投信）",
          "is_founder_family": false
        },
        {
          "rank": 4,
          "name": "日産化学 取引先持株会",
          "shares": 3762000,
          "ratio": 2.8,
          "category": "employee",
          "category_label": "従業員持株会",
          "is_founder_family": false
        },
        {
          "rank": 5,
          "name": "STATE STREET BANK AND TRUST COMPANY 505103(常任代理人　株式会社みずほ銀行決済営業部)",
          "shares": 1878000,
          "ratio": 1.4,
          "category": "foreign",
          "category_label": "外国機関投資家",
          "is_founder_family": false
        },
        {
          "rank": 6,
          "name": "明治安田生命保険相互会社",
          "shares": 1861000,
          "ratio": 1.39,
          "category": "financial",
          "category_label": "銀行・保険",
          "is_founder_family": false
        },
        {
          "rank": 7,
          "name": "JP MORGAN CHASE BANK 385781(常任代理人　株式会社みずほ銀行決済営業部)",
          "shares": 1833000,
          "ratio": 1.37,
          "category": "foreign",
          "category_label": "外国機関投資家",
          "is_founder_family": false
        },
        {
          "rank": 8,
          "name": "STATE STREET BANK AND TRUST COMPANY 505001(常任代理人　株式会社みずほ銀行決済営業部)",
          "shares": 1807000,
          "ratio": 1.35,
          "category": "foreign",
          "category_label": "外国機関投資家",
          "is_founder_family": false
        },
        {
          "rank": 9,
          "name": "HSBC HONG KONG-TREASURY SERVICES A/C ASIAN EQUITIES DERIVATIVES(常任代理人　香港上海銀行東京支店セキュリティーズ・サービシズ・オペレーションズ)",
          "shares": 1726000,
          "ratio": 1.29,
          "category": "foreign",
          "category_label": "外国機関投資家",
          "is_founder_family": false
        },
        {
          "rank": 10,
          "name": "JPモルガン証券株式会社",
          "shares": 1685000,
          "ratio": 1.26,
          "category": "securities",
          "category_label": "証券会社",
          "is_founder_family": false
        }
      ],
      "summary": {
        "by_category": {
          "trust": 41.0,
          "employee": 2.8,
          "foreign": 5.41,
          "financial": 1.39,
          "securities": 1.26
        },
        "individual_total": 0,
        "top10_total": 51.86
      }
    }
  ]
}