{
  "week": "2026-W18",
  "date": "2026/05/01",
  "title": "4/27〜5/1 週次マーケットレポート",
  "generated_at": "2026/05/01",
  "summary": {
    "avg_pct_1w": 1.71,
    "rise_count": 40,
    "fall_count": 27,
    "total_themes": 67,
    "top5_themes": [
      {
        "theme": "SaaS",
        "pct": 8.97
      },
      {
        "theme": "生成AI",
        "pct": 8.41
      },
      {
        "theme": "サイバーセキュリティ",
        "pct": 8.09
      },
      {
        "theme": "エッジAI",
        "pct": 7.08
      },
      {
        "theme": "通信",
        "pct": 7.04
      }
    ],
    "bot5_themes": [
      {
        "theme": "LNG",
        "pct": -4.24
      },
      {
        "theme": "石油",
        "pct": -3.83
      },
      {
        "theme": "造船",
        "pct": -2.73
      },
      {
        "theme": "建設・インフラ",
        "pct": -2.67
      },
      {
        "theme": "国土強靭化計画",
        "pct": -2.48
      }
    ]
  },
  "report": "## 市場概況（4/27〜5/1）\n\n今週の日本株式テーマ市場は、67テーマ中40テーマ（60%）が週間プラスとなり、テーマ平均騰落率は+1.71%と小幅な回復基調を示しました。前週比でAI・クラウド系の成長テーマが全体を牽引し、エネルギー・インフラ系テーマは続落する形となりました。\n\n> **注記**：4/29（昭和の日）は国民の祝日のため市場休場。今週の市場営業日は4/27（月）・4/28（火）・4/30（水）・5/1（木）の4日間です。\n\n---\n\n## 上昇テーマ（週間騰落率）\n\n### 1位：SaaS（+8.97%）\n\nSaaSが今週のトップテーマとなり、週間騰落率は+8.97%を記録しました。出来高も前月比+31.1%と大幅に増加しており、機関投資家による本格的な資金流入が確認されています。米国のSaaS大手の好決算が日本のSaaS関連株にも波及し、クラウド移行需要の継続性を評価する動きが見られます。月次騰落率は+21.4%、年間騰落率は+15.8%とあらゆる時間軸で安定した上昇トレンドを示しており、構造的な成長トレンドとして位置づけられます。\n\nStockWaveJPのモメンタム判定では「🔥上昇中」を示しており、出来高確認済みの最も強い買いシグナルが点灯しています。当面は押し目買いのタイミングを計りながら、中期保有を前提とした積極的な投資姿勢が合理的と考えられます。\n\n### 2位：生成AI（+8.41%）\n\n生成AIテーマは+8.41%と2位につけました。出来高は前月比+27.4%と拡大しており、機関投資家の参入が本格化しています。国内企業のAI活用推進・大型導入発表が相次いでおり、AIソフトウェアの開発企業からシステムインテグレーターまで幅広い銘柄に資金が向かっています。月次騰落率は+13.9%、年間騰落率は+15.8%と各時間軸で安定しており、「流行」ではなく「構造変化」として市場が認識し始めていることを示しています。\n\n### 3位：サイバーセキュリティ（+8.09%）\n\nサイバーセキュリティは+8.09%。出来高は前月比+26.9%と3週連続で平均超えとなっており、持続的な機関投資家の累積買いが確認されています。経済安全保障法に基づく政府のセキュリティ投資拡大が継続的な需要を生み出しており、景気動向に左右されにくい「守りの成長テーマ」として評価が高まっています。年間騰落率は+17.5%と全テーマ中でも高水準を維持しています。\n\n### 4位：エッジAI（+7.08%）\n\nエッジAIが+7.08%。クラウドではなくデバイスやロボット・製造設備に直接AI機能を組み込む「フィジカルAI」の概念が浸透してきており、ルネサスエレクトロニクスやオムロンへの注目が高まっています。NVIDIA等がロボット向け基盤モデルを発表したことで、日本のエッジAI半導体・制御機器メーカーへの期待が先行している形です。\n\n### 5位：通信（+7.04%）\n\n通信テーマが+7.04%でトップ5入り。NTTグループのIOWN（革新的光通信ネットワーク構想）が中長期の成長ストーリーとして機関投資家に認知されており、通信インフラと光通信の交差点として継続的な資金流入が続いています。\n\n---\n\n## 下落テーマ（週間騰落率）\n\n### LNG（-4.24%）・石油（-3.83%）\n\nエネルギー系テーマは今週も続落。世界的な原油・天然ガス価格の軟調推移に加え、脱炭素・エネルギー転換ナラティブがバリュエーションへの割引要因となっています。石油・LNG銘柄は配当利回りのサポートは残るものの、モメンタムの観点では「❄️下落中」シグナルを示しており、新規の買い参入は慎重な姿勢が適切です。\n\n### 造船（-2.73%）・建設・インフラ（-2.67%）・国土強靭化計画（-2.48%）\n\n造船・インフラ系テーマは前週の利益確定売りが続いており、週間で小幅な下落となりました。ただし、政府の防衛費増額・国土強靭化予算の大枠は変わらず、構造的な需要基盤は維持されています。モメンタムの一時的な後退を「押し目」として捉え、中長期での再エントリーポイントを見極める局面と判断します。\n\n---\n\n## 出来高分析：機関投資家の資金フロー\n\n今週、特に注目すべき出来高パターンを記録したテーマ：\n\n- **SaaS・生成AI**：大口機関の継続的な積み上げを示すブロックトレードが確認\n- **サイバーセキュリティ**：3週連続での出来高拡大は機関投資家の中期目線での組入れを示唆\n- **防衛・航空**：週間の価格変動は小さいが、出来高の水準は前月平均+28%と堅調維持\n\n出来高の大きいテーマへの資金流入が「投機」か「投資」かを判断するうえで、StockWaveJPの「売買代金」指標が有効です。売買代金が高水準かつ騰落率もプラスのテーマは機関投資家の本格参入を示し、トレンドの持続性が高いとみられます。\n\n---\n\n## マクロ環境\n\n**ドル円**：150〜153円のレンジ内で推移し、急激な円高・円安リスクは限定的でした。半導体製造装置など輸出関連の技術株にとっては概ねニュートラルな環境。\n\n**日銀**：今週は目立った政策コミュニケーションなし。市場コンセンサスは2026年中に追加利上げ1〜2回という見方で安定しており、銀行・金融テーマの中期的支援材料は継続。\n\n**GWに向けた注意点**：5/3〜5/6はゴールデンウィーク連休のため市場休場。連休中の米国市場の動向（特にFRB高官発言・米景気指標）が連休明けの相場に影響する可能性があります。来週の市場再開時は、休場期間中の海外環境変化を踏まえたポジション調整に注意が必要です。\n\n---\n\n## 来週（5/7〜）の注目イベント\n\n- **米国企業決算**：半導体・AI関連大手の決算発表→日本のAI供給網テーマへの直接的な影響\n- **日本企業3月期決算ラッシュ**：アドバンテスト・東京エレクトロンなど主要半導体関連企業の本決算\n- **米雇用統計（5/2発表）の影響の消化**：FRBの利下げ時期見通しの変化がリスク選好に影響\n- **ドル円動向**：円高方向への動きは輸出関連テーマの利益確定売りトリガーになりやすい\n\n---\n\n## 投資戦略まとめ\n\n| テーマ | モメンタム | 推奨 |\n|--------|-----------|------|\n| SaaS / 生成AI / サイバーセキュリティ | 🔥上昇中 | 中核ポジションとして保有継続 |\n| エッジAI / 通信 / IOWN | ↗上昇転換 | 押し目でのエントリー検討 |\n| 銀行・金融 | →横ばい | 中期目線での積立が合理的 |\n| 石油 / LNG | ❄️下落中 | 新規買いは見送り |\n| 造船 / インフラ | ↘下落転換 | 中長期での押し目待ち |\n\n> **免責事項**：本レポートはStockWaveJPのマーケットデータに基づく参考情報であり、特定の銘柄の売買を推奨するものではありません。投資判断は必ずご自身でお決めください。"
}