{"themes_5d":{"period":"5d","themes":[{"theme":"フィンテック","pct":-0.89,"up":false,"stock_count":4,"volume":6256150,"volume_chg":-0.6,"trade_value":15682359000},{"theme":"通信","pct":-1.22,"up":false,"stock_count":4,"volume":342268500,"volume_chg":35.4,"trade_value":90306180625},{"theme":"銀行・金融","pct":-1.3,"up":false,"stock_count":6,"volume":76302000,"volume_chg":7.9,"trade_value":223559451475},{"theme":"ヘルスケア・介護","pct":-1.41,"up":false,"stock_count":5,"volume":18384500,"volume_chg":-4.2,"trade_value":53236081025},{"theme":"観光・ホテル・レジャー","pct":-1.52,"up":false,"stock_count":4,"volume":12723850,"volume_chg":-1.2,"trade_value":33192965675},{"theme":"AI・クラウド","pct":-2.27,"up":false,"stock_count":8,"volume":32648500,"volume_chg":4.7,"trade_value":133407478700},{"theme":"輸送・物流","pct":-2.43,"up":false,"stock_count":5,"volume":30776050,"volume_chg":2.0,"trade_value":135020957900},{"theme":"脱炭素・ESG","pct":-2.44,"up":false,"stock_count":4,"volume":120809100,"volume_chg":15.6,"trade_value":133924376475},{"theme":"保険","pct":-2.8,"up":false,"stock_count":5,"volume":21339900,"volume_chg":27.2,"trade_value":74062381150},{"theme":"地方銀行","pct":-2.88,"up":false,"stock_count":4,"volume":5898450,"volume_chg":-2.5,"trade_value":9965575350},{"theme":"半導体","pct":-3.13,"up":false,"stock_count":9,"volume":34774500,"volume_chg":-9.5,"trade_value":502485476400},{"theme":"ゲーム・エンタメ","pct":-3.38,"up":false,"stock_count":7,"volume":32300700,"volume_chg":-4.8,"trade_value":162259920300},{"theme":"再生可能エネルギー","pct":-3.51,"up":false,"stock_count":4,"volume":36602750,"volume_chg":32.4,"trade_value":123544206400},{"theme":"小売・EC","pct":-3.62,"up":false,"stock_count":5,"volume":19246950,"volume_chg":17.3,"trade_value":93857375700},{"theme":"鉄鋼・素材","pct":-3.99,"up":false,"stock_count":4,"volume":41723100,"volume_chg":49.0,"trade_value":76159210675},{"theme":"造船","pct":-4.09,"up":false,"stock_count":2,"volume":6689250,"volume_chg":-3.2,"trade_value":39559309500},{"theme":"医薬品・バイオ","pct":-4.66,"up":false,"stock_count":6,"volume":25289000,"volume_chg":12.1,"trade_value":100029468950},{"theme":"食品・飲料","pct":-4.72,"up":false,"stock_count":6,"volume":17864700,"volume_chg":38.1,"trade_value":48759147600},{"theme":"農業・フードテック","pct":-4.79,"up":false,"stock_count":3,"volume":18375200,"volume_chg":28.6,"trade_value":16067447450},{"theme":"教育・HR・人材","pct":-4.93,"up":false,"stock_count":3,"volume":5312300,"volume_chg":41.5,"trade_value":32091142650},{"theme":"ロボット・自動化","pct":-4.94,"up":false,"stock_count":6,"volume":10724100,"volume_chg":19.8,"trade_value":82933025800},{"theme":"化学","pct":-4.97,"up":false,"stock_count":6,"volume":46309250,"volume_chg":38.4,"trade_value":112046164913},{"theme":"EV・電気自動車","pct":-4.99,"up":false,"stock_count":8,"volume":115983300,"volume_chg":18.7,"trade_value":189716881233},{"theme":"宇宙・衛星","pct":-6.07,"up":false,"stock_count":3,"volume":23768150,"volume_chg":1.6,"trade_value":95689858600},{"theme":"防衛・航空宇宙","pct":-6.24,"up":false,"stock_count":5,"volume":46778800,"volume_chg":0.8,"trade_value":234615193650},{"theme":"建設・インフラ","pct":-6.29,"up":false,"stock_count":5,"volume":13434400,"volume_chg":50.5,"trade_value":60404558050},{"theme":"不動産","pct":-7.03,"up":false,"stock_count":5,"volume":16751000,"volume_chg":6.6,"trade_value":44757615775},{"theme":"レアアース・資源","pct":-8.63,"up":false,"stock_count":3,"volume":9930400,"volume_chg":55.9,"trade_value":65888623400},{"theme":"サイバーセキュリティ","pct":-9.54,"up":false,"stock_count":3,"volume":355950,"volume_chg":90.9,"trade_value":1581477700},{"theme":"ドローン","pct":-13.86,"up":false,"stock_count":2,"volume":815450,"volume_chg":-39.5,"trade_value":1155492650}],"summary":{"total":30,"rise":0,"fall":30,"avg":-4.42,"top":{"theme":"フィンテック","pct":-0.89,"up":false,"stock_count":4,"volume":6256150,"volume_chg":-0.6,"trade_value":15682359000},"bot":{"theme":"ドローン","pct":-13.86,"up":false,"stock_count":2,"volume":815450,"volume_chg":-39.5,"trade_value":1155492650}},"updated_at":"2026/03/23 12:34 JST"},"themes_1mo":{"period":"1mo","themes":[{"theme":"ドローン","pct":13.18,"up":true,"stock_count":2,"volume":1571611,"volume_chg":4.9,"trade_value":2226972944},{"theme":"フィンテック","pct":6.34,"up":true,"stock_count":4,"volume":7655599,"volume_chg":-46.9,"trade_value":18728903692},{"theme":"AI・クラウド","pct":5.76,"up":true,"stock_count":8,"volume":35938709,"volume_chg":-36.8,"trade_value":146993234397},{"theme":"ゲーム・エンタメ","pct":5.23,"up":true,"stock_count":7,"volume":44317062,"volume_chg":-7.3,"trade_value":244661939985},{"theme":"輸送・物流","pct":4.57,"up":true,"stock_count":5,"volume":25946064,"volume_chg":-15.4,"trade_value":110458890081},{"theme":"再生可能エネルギー","pct":0.38,"up":true,"stock_count":4,"volume":29170210,"volume_chg":22.1,"trade_value":98042442232},{"theme":"ヘルスケア・介護","pct":-0.19,"up":false,"stock_count":5,"volume":22467087,"volume_chg":-20.8,"trade_value":59341815036},{"theme":"通信","pct":-0.43,"up":false,"stock_count":4,"volume":338448243,"volume_chg":-10.0,"trade_value":87214368244},{"theme":"教育・HR・人材","pct":-0.52,"up":false,"stock_count":3,"volume":5415944,"volume_chg":-38.0,"trade_value":33130976833},{"theme":"サイバーセキュリティ","pct":-4.1,"up":false,"stock_count":3,"volume":352954,"volume_chg":-39.1,"trade_value":1276943332},{"theme":"宇宙・衛星","pct":-6.65,"up":false,"stock_count":3,"volume":28496322,"volume_chg":-39.7,"trade_value":112507683688},{"theme":"防衛・航空宇宙","pct":-7.46,"up":false,"stock_count":5,"volume":54040288,"volume_chg":-33.9,"trade_value":265192531843},{"theme":"保険","pct":-7.49,"up":false,"stock_count":5,"volume":20334953,"volume_chg":-21.9,"trade_value":70874179920},{"theme":"医薬品・バイオ","pct":-8.09,"up":false,"stock_count":6,"volume":24544419,"volume_chg":-14.6,"trade_value":93923686686},{"theme":"観光・ホテル・レジャー","pct":-8.98,"up":false,"stock_count":4,"volume":13787853,"volume_chg":-13.5,"trade_value":35770985254},{"theme":"小売・EC","pct":-9.86,"up":false,"stock_count":5,"volume":20431453,"volume_chg":-17.1,"trade_value":94340473975},{"theme":"食品・飲料","pct":-10.15,"up":false,"stock_count":6,"volume":16632218,"volume_chg":-20.5,"trade_value":43054235569},{"theme":"脱炭素・ESG","pct":-10.28,"up":false,"stock_count":4,"volume":100919921,"volume_chg":-14.8,"trade_value":122533979298},{"theme":"不動産","pct":-11.32,"up":false,"stock_count":5,"volume":19007398,"volume_chg":-10.4,"trade_value":51560248170},{"theme":"半導体","pct":-11.63,"up":false,"stock_count":9,"volume":39336963,"volume_chg":-18.7,"trade_value":594052521241},{"theme":"銀行・金融","pct":-11.69,"up":false,"stock_count":6,"volume":86005488,"volume_chg":-29.4,"trade_value":251589506465},{"theme":"化学","pct":-12.23,"up":false,"stock_count":6,"volume":47406187,"volume_chg":-4.4,"trade_value":108974721148},{"theme":"ロボット・自動化","pct":-13.48,"up":false,"stock_count":6,"volume":11924376,"volume_chg":-28.9,"trade_value":93428432509},{"theme":"地方銀行","pct":-13.55,"up":false,"stock_count":4,"volume":6643143,"volume_chg":-28.1,"trade_value":11708070454},{"theme":"EV・電気自動車","pct":-13.91,"up":false,"stock_count":8,"volume":116080730,"volume_chg":-12.2,"trade_value":193423096334},{"theme":"農業・フードテック","pct":-15.18,"up":false,"stock_count":3,"volume":19322765,"volume_chg":-23.0,"trade_value":16404499849},{"theme":"鉄鋼・素材","pct":-15.22,"up":false,"stock_count":4,"volume":41370053,"volume_chg":-35.7,"trade_value":65546458121},{"theme":"建設・インフラ","pct":-15.59,"up":false,"stock_count":5,"volume":10348998,"volume_chg":-30.1,"trade_value":49325851598},{"theme":"レアアース・資源","pct":-18.96,"up":false,"stock_count":3,"volume":6888210,"volume_chg":-37.8,"trade_value":47296363421},{"theme":"造船","pct":-19.16,"up":false,"stock_count":2,"volume":6079877,"volume_chg":-31.7,"trade_value":35780351366}],"summary":{"total":30,"rise":6,"fall":24,"avg":-7.02,"top":{"theme":"ドローン","pct":13.18,"up":true,"stock_count":2,"volume":1571611,"volume_chg":4.9,"trade_value":2226972944},"bot":{"theme":"造船","pct":-19.16,"up":false,"stock_count":2,"volume":6079877,"volume_chg":-31.7,"trade_value":35780351366}},"updated_at":"2026/03/23 12:34 JST"},"themes_3mo":{"period":"3mo","themes":[{"theme":"ドローン","pct":60.66,"up":true,"stock_count":2,"volume":1268407,"volume_chg":11.2,"trade_value":1797332921},{"theme":"レアアース・資源","pct":26.51,"up":true,"stock_count":3,"volume":9501191,"volume_chg":-23.0,"trade_value":65359268020},{"theme":"防衛・航空宇宙","pct":23.06,"up":true,"stock_count":5,"volume":75405726,"volume_chg":38.9,"trade_value":368069437859},{"theme":"再生可能エネルギー","pct":21.99,"up":true,"stock_count":4,"volume":31108706,"volume_chg":53.1,"trade_value":101584214726},{"theme":"半導体","pct":18.15,"up":true,"stock_count":9,"volume":44686639,"volume_chg":1.9,"trade_value":676764275278},{"theme":"造船","pct":15.6,"up":true,"stock_count":2,"volume":9353099,"volume_chg":8.6,"trade_value":54667988235},{"theme":"地方銀行","pct":13.36,"up":true,"stock_count":4,"volume":7515120,"volume_chg":34.0,"trade_value":13881708163},{"theme":"輸送・物流","pct":11.88,"up":true,"stock_count":5,"volume":24441269,"volume_chg":58.9,"trade_value":97202822171},{"theme":"不動産","pct":8.11,"up":true,"stock_count":5,"volume":20629030,"volume_chg":10.5,"trade_value":56597958554},{"theme":"農業・フードテック","pct":5.84,"up":true,"stock_count":3,"volume":23330427,"volume_chg":27.1,"trade_value":22598246040},{"theme":"医薬品・バイオ","pct":5.79,"up":true,"stock_count":6,"volume":26478822,"volume_chg":-5.8,"trade_value":102221898145},{"theme":"食品・飲料","pct":4.62,"up":true,"stock_count":6,"volume":19683791,"volume_chg":17.6,"trade_value":52496497466},{"theme":"ロボット・自動化","pct":4.46,"up":true,"stock_count":6,"volume":14830208,"volume_chg":10.2,"trade_value":120249958834},{"theme":"鉄鋼・素材","pct":4.29,"up":true,"stock_count":4,"volume":51949466,"volume_chg":16.0,"trade_value":89764246452},{"theme":"保険","pct":3.7,"up":true,"stock_count":5,"volume":24238822,"volume_chg":16.1,"trade_value":83842289826},{"theme":"宇宙・衛星","pct":3.52,"up":true,"stock_count":3,"volume":42949088,"volume_chg":54.6,"trade_value":168533574467},{"theme":"建設・インフラ","pct":3.36,"up":true,"stock_count":5,"volume":13816554,"volume_chg":42.4,"trade_value":65338180923},{"theme":"銀行・金融","pct":3.01,"up":true,"stock_count":6,"volume":105036930,"volume_chg":17.9,"trade_value":314223841223},{"theme":"脱炭素・ESG","pct":2.72,"up":true,"stock_count":4,"volume":106233170,"volume_chg":18.5,"trade_value":144651469363},{"theme":"化学","pct":1.86,"up":true,"stock_count":6,"volume":49312802,"volume_chg":27.9,"trade_value":114794422967},{"theme":"EV・電気自動車","pct":-4.36,"up":false,"stock_count":8,"volume":128301303,"volume_chg":30.0,"trade_value":230008124106},{"theme":"観光・ホテル・レジャー","pct":-5.18,"up":false,"stock_count":4,"volume":14267334,"volume_chg":44.6,"trade_value":36811983313},{"theme":"ゲーム・エンタメ","pct":-6.36,"up":false,"stock_count":7,"volume":46155939,"volume_chg":43.2,"trade_value":232511350819},{"theme":"通信","pct":-6.92,"up":false,"stock_count":4,"volume":349235660,"volume_chg":41.9,"trade_value":98023256000},{"theme":"サイバーセキュリティ","pct":-7.62,"up":false,"stock_count":3,"volume":537045,"volume_chg":-3.6,"trade_value":2108626335},{"theme":"小売・EC","pct":-8.16,"up":false,"stock_count":5,"volume":23917709,"volume_chg":4.4,"trade_value":108473053765},{"theme":"ヘルスケア・介護","pct":-12.41,"up":false,"stock_count":5,"volume":26552254,"volume_chg":64.5,"trade_value":71857085615},{"theme":"AI・クラウド","pct":-20.19,"up":false,"stock_count":8,"volume":51677697,"volume_chg":69.1,"trade_value":211337262634},{"theme":"フィンテック","pct":-27.28,"up":false,"stock_count":4,"volume":9767645,"volume_chg":67.2,"trade_value":23591279086},{"theme":"教育・HR・人材","pct":-29.09,"up":false,"stock_count":3,"volume":8301777,"volume_chg":84.2,"trade_value":50926547031}],"summary":{"total":30,"rise":20,"fall":10,"avg":3.83,"top":{"theme":"ドローン","pct":60.66,"up":true,"stock_count":2,"volume":1268407,"volume_chg":11.2,"trade_value":1797332921},"bot":{"theme":"教育・HR・人材","pct":-29.09,"up":false,"stock_count":3,"volume":8301777,"volume_chg":84.2,"trade_value":50926547031}},"updated_at":"2026/03/23 12:34 JST"},"themes_6mo":{"period":"6mo","themes":[{"theme":"レアアース・資源","pct":87.87,"up":true,"stock_count":3,"volume":11196598,"volume_chg":380.9,"trade_value":68248450845},{"theme":"造船","pct":35.7,"up":true,"stock_count":2,"volume":8519443,"volume_chg":-16.6,"trade_value":49226827868},{"theme":"ドローン","pct":35.21,"up":true,"stock_count":2,"volume":1177430,"volume_chg":16.7,"trade_value":1668419030},{"theme":"地方銀行","pct":34.91,"up":true,"stock_count":4,"volume":6382082,"volume_chg":11.2,"trade_value":12458480583},{"theme":"半導体","pct":34.46,"up":true,"stock_count":9,"volume":44108463,"volume_chg":-20.0,"trade_value":702045633308},{"theme":"建設・インフラ","pct":33.8,"up":true,"stock_count":5,"volume":11539750,"volume_chg":10.7,"trade_value":57449025320},{"theme":"防衛・航空宇宙","pct":26.39,"up":true,"stock_count":5,"volume":66863034,"volume_chg":3.9,"trade_value":328281153087},{"theme":"鉄鋼・素材","pct":25.98,"up":true,"stock_count":4,"volume":44195013,"volume_chg":48.0,"trade_value":86918313041},{"theme":"再生可能エネルギー","pct":21.7,"up":true,"stock_count":4,"volume":27825701,"volume_chg":12.1,"trade_value":90307710383},{"theme":"宇宙・衛星","pct":19.56,"up":true,"stock_count":3,"volume":36220508,"volume_chg":15.3,"trade_value":141950361483},{"theme":"ロボット・自動化","pct":19.34,"up":true,"stock_count":6,"volume":15719108,"volume_chg":9.8,"trade_value":120897744050},{"theme":"不動産","pct":18.4,"up":true,"stock_count":5,"volume":19566671,"volume_chg":-1.3,"trade_value":51785959925},{"theme":"銀行・金融","pct":17.24,"up":true,"stock_count":6,"volume":98183366,"volume_chg":8.6,"trade_value":294134422929},{"theme":"脱炭素・ESG","pct":16.19,"up":true,"stock_count":4,"volume":112243228,"volume_chg":-9.2,"trade_value":143030956831},{"theme":"医薬品・バイオ","pct":16.11,"up":true,"stock_count":6,"volume":27913662,"volume_chg":4.1,"trade_value":106769203006},{"theme":"保険","pct":11.71,"up":true,"stock_count":5,"volume":22103858,"volume_chg":-16.3,"trade_value":77739502637},{"theme":"農業・フードテック","pct":9.45,"up":true,"stock_count":3,"volume":20187224,"volume_chg":12.7,"trade_value":19250610226},{"theme":"輸送・物流","pct":8.02,"up":true,"stock_count":5,"volume":19513599,"volume_chg":40.5,"trade_value":77783246872},{"theme":"EV・電気自動車","pct":5.38,"up":true,"stock_count":8,"volume":113582728,"volume_chg":10.8,"trade_value":208151184645},{"theme":"化学","pct":4.96,"up":true,"stock_count":6,"volume":43185200,"volume_chg":23.7,"trade_value":102173079157},{"theme":"食品・飲料","pct":3.54,"up":true,"stock_count":6,"volume":18651865,"volume_chg":-8.5,"trade_value":50289102436},{"theme":"通信","pct":-4.0,"up":false,"stock_count":4,"volume":318701291,"volume_chg":7.1,"trade_value":84833192223},{"theme":"小売・EC","pct":-5.49,"up":false,"stock_count":5,"volume":23973876,"volume_chg":-3.5,"trade_value":112354064590},{"theme":"観光・ホテル・レジャー","pct":-10.68,"up":false,"stock_count":4,"volume":12369328,"volume_chg":19.9,"trade_value":31962545886},{"theme":"サイバーセキュリティ","pct":-14.59,"up":false,"stock_count":3,"volume":615844,"volume_chg":-31.6,"trade_value":2849420253},{"theme":"AI・クラウド","pct":-15.46,"up":false,"stock_count":8,"volume":41006033,"volume_chg":68.2,"trade_value":168053497325},{"theme":"ゲーム・エンタメ","pct":-15.95,"up":false,"stock_count":7,"volume":40815180,"volume_chg":50.6,"trade_value":206029739882},{"theme":"ヘルスケア・介護","pct":-25.28,"up":false,"stock_count":5,"volume":21396433,"volume_chg":25.0,"trade_value":60821262169},{"theme":"教育・HR・人材","pct":-25.74,"up":false,"stock_count":3,"volume":6497436,"volume_chg":10.1,"trade_value":39913483082},{"theme":"フィンテック","pct":-35.98,"up":false,"stock_count":4,"volume":8211996,"volume_chg":88.2,"trade_value":20357801966}],"summary":{"total":30,"rise":21,"fall":9,"avg":11.09,"top":{"theme":"レアアース・資源","pct":87.87,"up":true,"stock_count":3,"volume":11196598,"volume_chg":380.9,"trade_value":68248450845},"bot":{"theme":"フィンテック","pct":-35.98,"up":false,"stock_count":4,"volume":8211996,"volume_chg":88.2,"trade_value":20357801966}},"updated_at":"2026/03/23 12:34 JST"},"themes_1y":{"period":"1y","themes":[{"theme":"造船","pct":155.51,"up":true,"stock_count":2,"volume":8902956,"volume_chg":-30.6,"trade_value":50764053042},{"theme":"レアアース・資源","pct":108.23,"up":true,"stock_count":3,"volume":7754848,"volume_chg":239.7,"trade_value":49269321151},{"theme":"建設・インフラ","pct":101.33,"up":true,"stock_count":5,"volume":10972984,"volume_chg":23.4,"trade_value":54942468982},{"theme":"宇宙・衛星","pct":78.31,"up":true,"stock_count":3,"volume":38936548,"volume_chg":12.5,"trade_value":150619826263},{"theme":"半導体","pct":78.09,"up":true,"stock_count":9,"volume":53831613,"volume_chg":-8.0,"trade_value":860132711258},{"theme":"防衛・航空宇宙","pct":71.79,"up":true,"stock_count":5,"volume":71771798,"volume_chg":-12.1,"trade_value":350725859393},{"theme":"再生可能エネルギー","pct":50.3,"up":true,"stock_count":4,"volume":26703056,"volume_chg":3.8,"trade_value":85863319937},{"theme":"地方銀行","pct":49.81,"up":true,"stock_count":4,"volume":6101636,"volume_chg":-2.3,"trade_value":12232796969},{"theme":"鉄鋼・素材","pct":38.6,"up":true,"stock_count":4,"volume":38445032,"volume_chg":31.8,"trade_value":68007681086},{"theme":"脱炭素・ESG","pct":36.77,"up":true,"stock_count":4,"volume":123602349,"volume_chg":-7.4,"trade_value":150991523873},{"theme":"不動産","pct":36.52,"up":true,"stock_count":5,"volume":20074143,"volume_chg":1.9,"trade_value":53053384419},{"theme":"銀行・金融","pct":31.08,"up":true,"stock_count":6,"volume":94840311,"volume_chg":-8.5,"trade_value":282890000143},{"theme":"サイバーセキュリティ","pct":31.08,"up":true,"stock_count":3,"volume":844238,"volume_chg":-5.3,"trade_value":4270050900},{"theme":"医薬品・バイオ","pct":25.55,"up":true,"stock_count":6,"volume":27237247,"volume_chg":9.0,"trade_value":105163112626},{"theme":"ドローン","pct":25.07,"up":true,"stock_count":2,"volume":1066523,"volume_chg":-2.2,"trade_value":1511264182},{"theme":"化学","pct":19.6,"up":true,"stock_count":6,"volume":38473660,"volume_chg":12.0,"trade_value":90961830806},{"theme":"ロボット・自動化","pct":19.34,"up":true,"stock_count":6,"volume":15306938,"volume_chg":28.5,"trade_value":117070627799},{"theme":"保険","pct":17.65,"up":true,"stock_count":5,"volume":24482250,"volume_chg":4.4,"trade_value":84663782249},{"theme":"農業・フードテック","pct":17.16,"up":true,"stock_count":3,"volume":17909943,"volume_chg":10.0,"trade_value":18040275537},{"theme":"EV・電気自動車","pct":12.53,"up":true,"stock_count":8,"volume":111324792,"volume_chg":-4.6,"trade_value":201708178551},{"theme":"小売・EC","pct":11.3,"up":true,"stock_count":5,"volume":24774837,"volume_chg":-2.9,"trade_value":116109302929},{"theme":"輸送・物流","pct":9.57,"up":true,"stock_count":5,"volume":16719726,"volume_chg":-1.4,"trade_value":66311366636},{"theme":"食品・飲料","pct":7.09,"up":true,"stock_count":6,"volume":19202082,"volume_chg":31.5,"trade_value":51564592663},{"theme":"通信","pct":2.75,"up":true,"stock_count":4,"volume":302780966,"volume_chg":9.1,"trade_value":82778751695},{"theme":"観光・ホテル・レジャー","pct":-0.82,"up":false,"stock_count":4,"volume":11419111,"volume_chg":14.6,"trade_value":29390221466},{"theme":"AI・クラウド","pct":-0.83,"up":false,"stock_count":8,"volume":35694843,"volume_chg":39.0,"trade_value":147922693702},{"theme":"ヘルスケア・介護","pct":-10.7,"up":false,"stock_count":5,"volume":18873866,"volume_chg":32.0,"trade_value":57472105732},{"theme":"ゲーム・エンタメ","pct":-12.43,"up":false,"stock_count":7,"volume":33207149,"volume_chg":28.5,"trade_value":161986775929},{"theme":"フィンテック","pct":-18.2,"up":false,"stock_count":4,"volume":7992098,"volume_chg":38.1,"trade_value":21034226513},{"theme":"教育・HR・人材","pct":-27.3,"up":false,"stock_count":3,"volume":5865786,"volume_chg":18.0,"trade_value":35900710448}],"summary":{"total":30,"rise":24,"fall":6,"avg":32.16,"top":{"theme":"造船","pct":155.51,"up":true,"stock_count":2,"volume":8902956,"volume_chg":-30.6,"trade_value":50764053042},"bot":{"theme":"教育・HR・人材","pct":-27.3,"up":false,"stock_count":3,"volume":5865786,"volume_chg":18.0,"trade_value":35900710448}},"updated_at":"2026/03/23 12:34 JST"},"macro_1mo":{"period":"1mo","data":{"日経平均":[{"date":"2026-02-24","pct":0.0},{"date":"2026-02-25","pct":2.2},{"date":"2026-02-26","pct":2.5},{"date":"2026-02-27","pct":2.67},{"date":"2026-03-02","pct":1.28},{"date":"2026-03-03","pct":-1.82},{"date":"2026-03-04","pct":-5.37},{"date":"2026-03-05","pct":-3.56},{"date":"2026-03-06","pct":-2.97},{"date":"2026-03-09","pct":-8.01},{"date":"2026-03-10","pct":-5.36},{"date":"2026-03-11","pct":-4.01},{"date":"2026-03-12","pct":-5.0},{"date":"2026-03-13","pct":-6.11},{"date":"2026-03-16","pct":-6.23},{"date":"2026-03-17","pct":-6.32},{"date":"2026-03-18","pct":-3.63},{"date":"2026-03-19","pct":-6.89},{"date":"2026-03-23","pct":-10.01}],"S&P500":[{"date":"2026-02-24","pct":0.0},{"date":"2026-02-25","pct":0.81},{"date":"2026-02-26","pct":0.27},{"date":"2026-02-27","pct":-0.16},{"date":"2026-03-02","pct":-0.12},{"date":"2026-03-03","pct":-1.07},{"date":"2026-03-04","pct":-0.3},{"date":"2026-03-05","pct":-0.86},{"date":"2026-03-06","pct":-2.18},{"date":"2026-03-09","pct":-1.37},{"date":"2026-03-10","pct":-1.58},{"date":"2026-03-11","pct":-1.66},{"date":"2026-03-12","pct":-3.16},{"date":"2026-03-13","pct":-3.74},{"date":"2026-03-16","pct":-2.77},{"date":"2026-03-17","pct":-2.53},{"date":"2026-03-18","pct":-3.85},{"date":"2026-03-19","pct":-4.12},{"date":"2026-03-20","pct":-5.57}],"ドル円":[{"date":"2026-02-24","pct":0.0},{"date":"2026-02-25","pct":0.81},{"date":"2026-02-26","pct":1.01},{"date":"2026-02-27","pct":0.79},{"date":"2026-03-02","pct":1.29},{"date":"2026-03-03","pct":1.7},{"date":"2026-03-04","pct":2.03},{"date":"2026-03-05","pct":1.52},{"date":"2026-03-06","pct":1.87},{"date":"2026-03-09","pct":2.45},{"date":"2026-03-10","pct":2.08},{"date":"2026-03-11","pct":2.25},{"date":"2026-03-12","pct":2.87},{"date":"2026-03-13","pct":2.96},{"date":"2026-03-16","pct":3.19},{"date":"2026-03-17","pct":2.89},{"date":"2026-03-18","pct":2.75},{"date":"2026-03-19","pct":3.34},{"date":"2026-03-20","pct":2.13},{"date":"2026-03-23","pct":3.11}],"ナスダック":[{"date":"2026-02-24","pct":0.0},{"date":"2026-02-25","pct":1.26},{"date":"2026-02-26","pct":0.06},{"date":"2026-02-27","pct":-0.85},{"date":"2026-03-02","pct":-0.5},{"date":"2026-03-03","pct":-1.52},{"date":"2026-03-04","pct":-0.25},{"date":"2026-03-05","pct":-0.5},{"date":"2026-03-06","pct":-2.08},{"date":"2026-03-09","pct":-0.73},{"date":"2026-03-10","pct":-0.73},{"date":"2026-03-11","pct":-0.65},{"date":"2026-03-12","pct":-2.41},{"date":"2026-03-13","pct":-3.32},{"date":"2026-03-16","pct":-2.14},{"date":"2026-03-17","pct":-1.68},{"date":"2026-03-18","pct":-3.11},{"date":"2026-03-19","pct":-3.38},{"date":"2026-03-20","pct":-5.32}],"VIX":[{"date":"2026-02-24","pct":0.0},{"date":"2026-02-25","pct":-8.29},{"date":"2026-02-26","pct":-4.71},{"date":"2026-02-27","pct":1.59},{"date":"2026-03-02","pct":9.67},{"date":"2026-03-03","pct":20.56},{"date":"2026-03-04","pct":8.18},{"date":"2026-03-05","pct":21.48},{"date":"2026-03-06","pct":50.84},{"date":"2026-03-09","pct":30.43},{"date":"2026-03-10","pct":27.52},{"date":"2026-03-11","pct":23.94},{"date":"2026-03-12","pct":39.59},{"date":"2026-03-13","pct":39.08},{"date":"2026-03-16","pct":20.26},{"date":"2026-03-17","pct":14.42},{"date":"2026-03-18","pct":28.34},{"date":"2026-03-19","pct":23.07},{"date":"2026-03-20","pct":36.98}]},"updated_at":"2026/03/23 12:34 JST"},"macro_1y":{"period":"1y","data":{"日経平均":[{"date":"2025-03-24","pct":0.0},{"date":"2025-03-25","pct":0.46},{"date":"2025-03-26","pct":1.11},{"date":"2025-03-27","pct":0.51},{"date":"2025-03-28","pct":-1.3},{"date":"2025-03-31","pct":-5.29},{"date":"2025-04-01","pct":-5.28},{"date":"2025-04-02","pct":-5.01},{"date":"2025-04-03","pct":-7.64},{"date":"2025-04-04","pct":-10.18},{"date":"2025-04-07","pct":-17.21},{"date":"2025-04-08","pct":-12.22},{"date":"2025-04-09","pct":-15.67},{"date":"2025-04-10","pct":-7.98},{"date":"2025-04-11","pct":-10.7},{"date":"2025-04-14","pct":-9.64},{"date":"2025-04-15","pct":-8.88},{"date":"2025-04-16","pct":-9.81},{"date":"2025-04-17","pct":-8.59},{"date":"2025-04-18","pct":-7.65},{"date":"2025-04-21","pct":-8.85},{"date":"2025-04-22","pct":-9.01},{"date":"2025-04-23","pct":-7.29},{"date":"2025-04-24","pct":-6.83},{"date":"2025-04-25","pct":-5.06},{"date":"2025-04-28","pct":-4.7},{"date":"2025-04-30","pct":-4.16},{"date":"2025-05-01","pct":-3.07},{"date":"2025-05-02","pct":-2.07},{"date":"2025-05-07","pct":-2.2},{"date":"2025-05-08","pct":-1.81},{"date":"2025-05-09","pct":-0.28},{"date":"2025-05-12","pct":0.1},{"date":"2025-05-13","pct":1.53},{"date":"2025-05-14","pct":1.38},{"date":"2025-05-15","pct":0.39},{"date":"2025-05-16","pct":0.39},{"date":"2025-05-19","pct":-0.29},{"date":"2025-05-20","pct":-0.21},{"date":"2025-05-21","pct":-0.82},{"date":"2025-05-22","pct":-1.66},{"date":"2025-05-23","pct":-1.19},{"date":"2025-05-26","pct":-0.2},{"date":"2025-05-27","pct":0.31},{"date":"2025-05-28","pct":0.3},{"date":"2025-05-29","pct":2.19},{"date":"2025-05-30","pct":0.95},{"date":"2025-06-02","pct":-0.37},{"date":"2025-06-03","pct":-0.43},{"date":"2025-06-04","pct":0.37},{"date":"2025-06-05","pct":-0.14},{"date":"2025-06-06","pct":0.35},{"date":"2025-06-09","pct":1.28},{"date":"2025-06-10","pct":1.6},{"date":"2025-06-11","pct":2.16},{"date":"2025-06-12","pct":1.5},{"date":"2025-06-13","pct":0.6},{"date":"2025-06-16","pct":1.87},{"date":"2025-06-17","pct":2.47},{"date":"2025-06-18","pct":3.39},{"date":"2025-06-19","pct":2.34},{"date":"2025-06-20","pct":2.11},{"date":"2025-06-23","pct":1.98},{"date":"2025-06-24","pct":3.14},{"date":"2025-06-25","pct":3.55},{"date":"2025-06-26","pct":5.25},{"date":"2025-06-27","pct":6.76},{"date":"2025-06-30","pct":7.65},{"date":"2025-07-01","pct":6.32},{"date":"2025-07-02","pct":5.73},{"date":"2025-07-03","pct":5.79},{"date":"2025-07-04","pct":5.86},{"date":"2025-07-07","pct":5.26},{"date":"2025-07-08","pct":5.53},{"date":"2025-07-09","pct":5.88},{"date":"2025-07-10","pct":5.42},{"date":"2025-07-11","pct":5.21},{"date":"2025-07-14","pct":4.92},{"date":"2025-07-15","pct":5.5},{"date":"2025-07-16","pct":5.46},{"date":"2025-07-17","pct":6.1},{"date":"2025-07-18","pct":5.88},{"date":"2025-07-22","pct":5.76},{"date":"2025-07-23","pct":9.47},{"date":"2025-07-24","pct":11.22},{"date":"2025-07-25","pct":10.23},{"date":"2025-07-28","pct":9.01},{"date":"2025-07-29","pct":8.15},{"date":"2025-07-30","pct":8.1},{"date":"2025-07-31","pct":9.2},{"date":"2025-08-01","pct":8.49},{"date":"2025-08-04","pct":7.13},{"date":"2025-08-05","pct":7.82},{"date":"2025-08-06","pct":8.47},{"date":"2025-08-07","pct":9.18},{"date":"2025-08-08","pct":11.2},{"date":"2025-08-12","pct":13.59},{"date":"2025-08-13","pct":15.07},{"date":"2025-08-14","pct":13.4},{"date":"2025-08-15","pct":15.34},{"date":"2025-08-18","pct":16.24},{"date":"2025-08-19","pct":15.79},{"date":"2025-08-20","pct":14.04},{"date":"2025-08-21","pct":13.3},{"date":"2025-08-22","pct":13.36},{"date":"2025-08-25","pct":13.82},{"date":"2025-08-26","pct":12.73},{"date":"2025-08-27","pct":13.06},{"date":"2025-08-28","pct":13.88},{"date":"2025-08-29","pct":13.59},{"date":"2025-09-01","pct":12.18},{"date":"2025-09-02","pct":12.5},{"date":"2025-09-03","pct":11.51},{"date":"2025-09-04","pct":13.22},{"date":"2025-09-05","pct":14.39},{"date":"2025-09-08","pct":16.05},{"date":"2025-09-09","pct":15.56},{"date":"2025-09-10","pct":16.56},{"date":"2025-09-11","pct":17.99},{"date":"2025-09-12","pct":19.04},{"date":"2025-09-16","pct":19.39},{"date":"2025-09-17","pct":19.1},{"date":"2025-09-18","pct":20.46},{"date":"2025-09-19","pct":19.78},{"date":"2025-09-22","pct":20.97},{"date":"2025-09-24","pct":21.33},{"date":"2025-09-25","pct":21.66},{"date":"2025-09-26","pct":20.6},{"date":"2025-09-29","pct":19.77},{"date":"2025-09-30","pct":19.47},{"date":"2025-10-01","pct":18.46},{"date":"2025-10-02","pct":19.49},{"date":"2025-10-03","pct":21.7},{"date":"2025-10-06","pct":27.48},{"date":"2025-10-07","pct":27.5},{"date":"2025-10-08","pct":26.93},{"date":"2025-10-09","pct":29.17},{"date":"2025-10-10","pct":27.87},{"date":"2025-10-14","pct":24.57},{"date":"2025-10-15","pct":26.76},{"date":"2025-10-16","pct":28.37},{"date":"2025-10-17","pct":26.52},{"date":"2025-10-20","pct":30.78},{"date":"2025-10-21","pct":31.13},{"date":"2025-10-22","pct":31.11},{"date":"2025-10-23","pct":29.34},{"date":"2025-10-24","pct":31.09},{"date":"2025-10-27","pct":34.31},{"date":"2025-10-28","pct":33.53},{"date":"2025-10-29","pct":36.43},{"date":"2025-10-30","pct":36.47},{"date":"2025-10-31","pct":39.36},{"date":"2025-11-04","pct":36.93},{"date":"2025-11-05","pct":33.51},{"date":"2025-11-06","pct":35.3},{"date":"2025-11-07","pct":33.68},{"date":"2025-11-10","pct":35.37},{"date":"2025-11-11","pct":35.19},{"date":"2025-11-12","pct":35.78},{"date":"2025-11-13","pct":36.36},{"date":"2025-11-14","pct":33.95},{"date":"2025-11-17","pct":33.81},{"date":"2025-11-18","pct":29.5},{"date":"2025-11-19","pct":29.06},{"date":"2025-11-20","pct":32.48},{"date":"2025-11-21","pct":29.29},{"date":"2025-11-25","pct":29.38},{"date":"2025-11-26","pct":31.78},{"date":"2025-11-27","pct":33.39},{"date":"2025-11-28","pct":33.62},{"date":"2025-12-01","pct":31.1},{"date":"2025-12-02","pct":31.1},{"date":"2025-12-03","pct":32.59},{"date":"2025-12-04","pct":35.68},{"date":"2025-12-05","pct":34.26},{"date":"2025-12-08","pct":34.5},{"date":"2025-12-09","pct":34.69},{"date":"2025-12-10","pct":34.55},{"date":"2025-12-11","pct":33.34},{"date":"2025-12-12","pct":35.17},{"date":"2025-12-15","pct":33.4},{"date":"2025-12-16","pct":31.31},{"date":"2025-12-17","pct":31.65},{"date":"2025-12-18","pct":30.29},{"date":"2025-12-19","pct":31.64},{"date":"2025-12-22","pct":34.02},{"date":"2025-12-23","pct":34.05},{"date":"2025-12-24","pct":33.86},{"date":"2025-12-25","pct":34.03},{"date":"2025-12-26","pct":34.94},{"date":"2025-12-29","pct":34.35},{"date":"2025-12-30","pct":33.85},{"date":"2026-01-05","pct":37.82},{"date":"2026-01-06","pct":39.64},{"date":"2026-01-07","pct":38.17},{"date":"2026-01-08","pct":35.92},{"date":"2026-01-09","pct":38.11},{"date":"2026-01-13","pct":42.39},{"date":"2026-01-14","pct":44.49},{"date":"2026-01-15","pct":43.88},{"date":"2026-01-16","pct":43.41},{"date":"2026-01-19","pct":42.48},{"date":"2026-01-20","pct":40.9},{"date":"2026-01-21","pct":40.33},{"date":"2026-01-22","pct":42.76},{"date":"2026-01-23","pct":43.18},{"date":"2026-01-26","pct":40.62},{"date":"2026-01-27","pct":41.81},{"date":"2026-01-28","pct":41.88},{"date":"2026-01-29","pct":41.92},{"date":"2026-01-30","pct":41.78},{"date":"2026-02-02","pct":40.01},{"date":"2026-02-03","pct":45.5},{"date":"2026-02-04","pct":44.36},{"date":"2026-02-05","pct":43.1},{"date":"2026-02-06","pct":44.26},{"date":"2026-02-09","pct":49.87},{"date":"2026-02-10","pct":53.29},{"date":"2026-02-12","pct":53.26},{"date":"2026-02-13","pct":51.41},{"date":"2026-02-16","pct":51.05},{"date":"2026-02-17","pct":50.41},{"date":"2026-02-18","pct":51.94},{"date":"2026-02-19","pct":52.81},{"date":"2026-02-20","pct":51.1},{"date":"2026-02-24","pct":52.42},{"date":"2026-02-25","pct":55.77},{"date":"2026-02-26","pct":56.22},{"date":"2026-02-27","pct":56.48},{"date":"2026-03-02","pct":54.37},{"date":"2026-03-03","pct":49.64},{"date":"2026-03-04","pct":44.24},{"date":"2026-03-05","pct":46.98},{"date":"2026-03-06","pct":47.89},{"date":"2026-03-09","pct":40.2},{"date":"2026-03-10","pct":44.25},{"date":"2026-03-11","pct":46.31},{"date":"2026-03-12","pct":44.79},{"date":"2026-03-13","pct":43.1},{"date":"2026-03-16","pct":42.92},{"date":"2026-03-17","pct":42.79},{"date":"2026-03-18","pct":46.88},{"date":"2026-03-19","pct":41.92},{"date":"2026-03-23","pct":37.16}],"S&P500":[{"date":"2025-03-24","pct":0.0},{"date":"2025-03-25","pct":0.16},{"date":"2025-03-26","pct":-0.96},{"date":"2025-03-27","pct":-1.29},{"date":"2025-03-28","pct":-3.24},{"date":"2025-03-31","pct":-2.7},{"date":"2025-04-01","pct":-2.33},{"date":"2025-04-02","pct":-1.67},{"date":"2025-04-03","pct":-6.43},{"date":"2025-04-04","pct":-12.02},{"date":"2025-04-07","pct":-12.23},{"date":"2025-04-08","pct":-13.61},{"date":"2025-04-09","pct":-5.39},{"date":"2025-04-10","pct":-8.66},{"date":"2025-04-11","pct":-7.01},{"date":"2025-04-14","pct":-6.27},{"date":"2025-04-15","pct":-6.43},{"date":"2025-04-16","pct":-8.53},{"date":"2025-04-17","pct":-8.41},{"date":"2025-04-21","pct":-10.57},{"date":"2025-04-22","pct":-8.32},{"date":"2025-04-23","pct":-6.79},{"date":"2025-04-24","pct":-4.9},{"date":"2025-04-25","pct":-4.2},{"date":"2025-04-28","pct":-4.14},{"date":"2025-04-29","pct":-3.58},{"date":"2025-04-30","pct":-3.44},{"date":"2025-05-01","pct":-2.83},{"date":"2025-05-02","pct":-1.4},{"date":"2025-05-05","pct":-2.03},{"date":"2025-05-06","pct":-2.79},{"date":"2025-05-07","pct":-2.36},{"date":"2025-05-08","pct":-1.8},{"date":"2025-05-09","pct":-1.87},{"date":"2025-05-12","pct":1.33},{"date":"2025-05-13","pct":2.06},{"date":"2025-05-14","pct":2.17},{"date":"2025-05-15","pct":2.59},{"date":"2025-05-16","pct":3.31},{"date":"2025-05-19","pct":3.4},{"date":"2025-05-20","pct":3.0},{"date":"2025-05-21","pct":1.34},{"date":"2025-05-22","pct":1.29},{"date":"2025-05-23","pct":0.61},{"date":"2025-05-27","pct":2.67},{"date":"2025-05-28","pct":2.1},{"date":"2025-05-29","pct":2.51},{"date":"2025-05-30","pct":2.5},{"date":"2025-06-02","pct":2.92},{"date":"2025-06-03","pct":3.52},{"date":"2025-06-04","pct":3.52},{"date":"2025-06-05","pct":2.98},{"date":"2025-06-06","pct":4.04},{"date":"2025-06-09","pct":4.13},{"date":"2025-06-10","pct":4.7},{"date":"2025-06-11","pct":4.42},{"date":"2025-06-12","pct":4.81},{"date":"2025-06-13","pct":3.63},{"date":"2025-06-16","pct":4.6},{"date":"2025-06-17","pct":3.73},{"date":"2025-06-18","pct":3.7},{"date":"2025-06-20","pct":3.47},{"date":"2025-06-23","pct":4.47},{"date":"2025-06-24","pct":5.63},{"date":"2025-06-25","pct":5.63},{"date":"2025-06-26","pct":6.48},{"date":"2025-06-27","pct":7.03},{"date":"2025-06-30","pct":7.58},{"date":"2025-07-01","pct":7.46},{"date":"2025-07-02","pct":7.97},{"date":"2025-07-03","pct":8.87},{"date":"2025-07-07","pct":8.02},{"date":"2025-07-08","pct":7.94},{"date":"2025-07-09","pct":8.59},{"date":"2025-07-10","pct":8.89},{"date":"2025-07-11","pct":8.53},{"date":"2025-07-14","pct":8.69},{"date":"2025-07-15","pct":8.26},{"date":"2025-07-16","pct":8.6},{"date":"2025-07-17","pct":9.19},{"date":"2025-07-18","pct":9.18},{"date":"2025-07-21","pct":9.33},{"date":"2025-07-22","pct":9.4},{"date":"2025-07-23","pct":10.25},{"date":"2025-07-24","pct":10.33},{"date":"2025-07-25","pct":10.77},{"date":"2025-07-28","pct":10.79},{"date":"2025-07-29","pct":10.46},{"date":"2025-07-30","pct":10.32},{"date":"2025-07-31","pct":9.91},{"date":"2025-08-01","pct":8.16},{"date":"2025-08-04","pct":9.75},{"date":"2025-08-05","pct":9.22},{"date":"2025-08-06","pct":10.01},{"date":"2025-08-07","pct":9.92},{"date":"2025-08-08","pct":10.78},{"date":"2025-08-11","pct":10.5},{"date":"2025-08-12","pct":11.76},{"date":"2025-08-13","pct":12.12},{"date":"2025-08-14","pct":12.15},{"date":"2025-08-15","pct":11.83},{"date":"2025-08-18","pct":11.82},{"date":"2025-08-19","pct":11.16},{"date":"2025-08-20","pct":10.89},{"date":"2025-08-21","pct":10.45},{"date":"2025-08-22","pct":12.13},{"date":"2025-08-25","pct":11.65},{"date":"2025-08-26","pct":12.11},{"date":"2025-08-27","pct":12.38},{"date":"2025-08-28","pct":12.73},{"date":"2025-08-29","pct":12.01},{"date":"2025-09-02","pct":11.23},{"date":"2025-09-03","pct":11.8},{"date":"2025-09-04","pct":12.74},{"date":"2025-09-05","pct":12.38},{"date":"2025-09-08","pct":12.62},{"date":"2025-09-09","pct":12.92},{"date":"2025-09-10","pct":13.25},{"date":"2025-09-11","pct":14.22},{"date":"2025-09-12","pct":14.16},{"date":"2025-09-15","pct":14.7},{"date":"2025-09-16","pct":14.55},{"date":"2025-09-17","pct":14.44},{"date":"2025-09-18","pct":14.99},{"date":"2025-09-19","pct":15.55},{"date":"2025-09-22","pct":16.06},{"date":"2025-09-23","pct":15.42},{"date":"2025-09-24","pct":15.09},{"date":"2025-09-25","pct":14.51},{"date":"2025-09-26","pct":15.19},{"date":"2025-09-29","pct":15.49},{"date":"2025-09-30","pct":15.97},{"date":"2025-10-01","pct":16.36},{"date":"2025-10-02","pct":16.43},{"date":"2025-10-03","pct":16.44},{"date":"2025-10-06","pct":16.87},{"date":"2025-10-07","pct":16.42},{"date":"2025-10-08","pct":17.1},{"date":"2025-10-09","pct":16.78},{"date":"2025-10-10","pct":13.61},{"date":"2025-10-13","pct":15.38},{"date":"2025-10-14","pct":15.2},{"date":"2025-10-15","pct":15.67},{"date":"2025-10-16","pct":14.94},{"date":"2025-10-17","pct":15.54},{"date":"2025-10-20","pct":16.78},{"date":"2025-10-21","pct":16.78},{"date":"2025-10-22","pct":16.16},{"date":"2025-10-23","pct":16.83},{"date":"2025-10-24","pct":17.76},{"date":"2025-10-27","pct":19.2},{"date":"2025-10-28","pct":19.48},{"date":"2025-10-29","pct":19.47},{"date":"2025-10-30","pct":18.29},{"date":"2025-10-31","pct":18.6},{"date":"2025-11-03","pct":18.8},{"date":"2025-11-04","pct":17.41},{"date":"2025-11-05","pct":17.84},{"date":"2025-11-06","pct":16.52},{"date":"2025-11-07","pct":16.67},{"date":"2025-11-10","pct":18.46},{"date":"2025-11-11","pct":18.71},{"date":"2025-11-12","pct":18.78},{"date":"2025-11-13","pct":16.82},{"date":"2025-11-14","pct":16.76},{"date":"2025-11-17","pct":15.69},{"date":"2025-11-18","pct":14.73},{"date":"2025-11-19","pct":15.16},{"date":"2025-11-20","pct":13.37},{"date":"2025-11-21","pct":14.48},{"date":"2025-11-24","pct":16.26},{"date":"2025-11-25","pct":17.31},{"date":"2025-11-26","pct":18.12},{"date":"2025-11-28","pct":18.75},{"date":"2025-12-01","pct":18.12},{"date":"2025-12-02","pct":18.41},{"date":"2025-12-03","pct":18.76},{"date":"2025-12-04","pct":18.89},{"date":"2025-12-05","pct":19.12},{"date":"2025-12-08","pct":18.71},{"date":"2025-12-09","pct":18.6},{"date":"2025-12-10","pct":19.4},{"date":"2025-12-11","pct":19.65},{"date":"2025-12-12","pct":18.38},{"date":"2025-12-15","pct":18.19},{"date":"2025-12-16","pct":17.91},{"date":"2025-12-17","pct":16.54},{"date":"2025-12-18","pct":17.46},{"date":"2025-12-19","pct":18.5},{"date":"2025-12-22","pct":19.26},{"date":"2025-12-23","pct":19.8},{"date":"2025-12-24","pct":20.19},{"date":"2025-12-26","pct":20.15},{"date":"2025-12-29","pct":19.73},{"date":"2025-12-30","pct":19.57},{"date":"2025-12-31","pct":18.69},{"date":"2026-01-02","pct":18.91},{"date":"2026-01-05","pct":19.67},{"date":"2026-01-06","pct":20.41},{"date":"2026-01-07","pct":20.0},{"date":"2026-01-08","pct":20.01},{"date":"2026-01-09","pct":20.78},{"date":"2026-01-12","pct":20.97},{"date":"2026-01-13","pct":20.74},{"date":"2026-01-14","pct":20.1},{"date":"2026-01-15","pct":20.41},{"date":"2026-01-16","pct":20.33},{"date":"2026-01-20","pct":17.85},{"date":"2026-01-21","pct":19.21},{"date":"2026-01-22","pct":19.87},{"date":"2026-01-23","pct":19.91},{"date":"2026-01-26","pct":20.51},{"date":"2026-01-27","pct":21.0},{"date":"2026-01-28","pct":20.99},{"date":"2026-01-29","pct":20.83},{"date":"2026-01-30","pct":20.31},{"date":"2026-02-02","pct":20.96},{"date":"2026-02-03","pct":19.94},{"date":"2026-02-04","pct":19.33},{"date":"2026-02-05","pct":17.87},{"date":"2026-02-06","pct":20.19},{"date":"2026-02-09","pct":20.76},{"date":"2026-02-10","pct":20.36},{"date":"2026-02-11","pct":20.35},{"date":"2026-02-12","pct":18.47},{"date":"2026-02-13","pct":18.53},{"date":"2026-02-17","pct":18.65},{"date":"2026-02-18","pct":19.31},{"date":"2026-02-19","pct":18.97},{"date":"2026-02-20","pct":19.8},{"date":"2026-02-23","pct":18.56},{"date":"2026-02-24","pct":19.46},{"date":"2026-02-25","pct":20.43},{"date":"2026-02-26","pct":19.79},{"date":"2026-02-27","pct":19.27},{"date":"2026-03-02","pct":19.32},{"date":"2026-03-03","pct":18.19},{"date":"2026-03-04","pct":19.11},{"date":"2026-03-05","pct":18.43},{"date":"2026-03-06","pct":16.86},{"date":"2026-03-09","pct":17.83},{"date":"2026-03-10","pct":17.58},{"date":"2026-03-11","pct":17.48},{"date":"2026-03-12","pct":15.69},{"date":"2026-03-13","pct":14.99},{"date":"2026-03-16","pct":16.16},{"date":"2026-03-17","pct":16.45},{"date":"2026-03-18","pct":14.86},{"date":"2026-03-19","pct":14.55},{"date":"2026-03-20","pct":12.81}],"ドル円":[{"date":"2025-03-24","pct":0.0},{"date":"2025-03-25","pct":0.73},{"date":"2025-03-26","pct":0.18},{"date":"2025-03-27","pct":0.53},{"date":"2025-03-28","pct":0.78},{"date":"2025-03-31","pct":-0.04},{"date":"2025-04-01","pct":0.16},{"date":"2025-04-02","pct":0.07},{"date":"2025-04-03","pct":-1.21},{"date":"2025-04-04","pct":-2.3},{"date":"2025-04-07","pct":-2.84},{"date":"2025-04-08","pct":-1.26},{"date":"2025-04-09","pct":-2.56},{"date":"2025-04-10","pct":-1.52},{"date":"2025-04-11","pct":-3.96},{"date":"2025-04-14","pct":-4.0},{"date":"2025-04-15","pct":-4.31},{"date":"2025-04-16","pct":-4.34},{"date":"2025-04-17","pct":-5.18},{"date":"2025-04-18","pct":-5.03},{"date":"2025-04-21","pct":-5.98},{"date":"2025-04-22","pct":-5.88},{"date":"2025-04-23","pct":-4.67},{"date":"2025-04-24","pct":-4.31},{"date":"2025-04-25","pct":-4.54},{"date":"2025-04-28","pct":-3.9},{"date":"2025-04-29","pct":-5.01},{"date":"2025-04-30","pct":-4.93},{"date":"2025-05-01","pct":-4.45},{"date":"2025-05-02","pct":-2.83},{"date":"2025-05-05","pct":-3.38},{"date":"2025-05-06","pct":-4.02},{"date":"2025-05-07","pct":-4.44},{"date":"2025-05-08","pct":-3.89},{"date":"2025-05-09","pct":-2.45},{"date":"2025-05-12","pct":-2.58},{"date":"2025-05-13","pct":-0.91},{"date":"2025-05-14","pct":-1.44},{"date":"2025-05-15","pct":-2.02},{"date":"2025-05-16","pct":-2.72},{"date":"2025-05-19","pct":-2.93},{"date":"2025-05-20","pct":-3.14},{"date":"2025-05-21","pct":-3.57},{"date":"2025-05-22","pct":-3.96},{"date":"2025-05-23","pct":-3.89},{"date":"2025-05-26","pct":-4.55},{"date":"2025-05-27","pct":-4.69},{"date":"2025-05-28","pct":-3.67},{"date":"2025-05-29","pct":-2.66},{"date":"2025-05-30","pct":-3.94},{"date":"2025-06-02","pct":-3.92},{"date":"2025-06-03","pct":-4.83},{"date":"2025-06-04","pct":-3.9},{"date":"2025-06-05","pct":-4.64},{"date":"2025-06-06","pct":-4.1},{"date":"2025-06-09","pct":-3.33},{"date":"2025-06-10","pct":-3.43},{"date":"2025-06-11","pct":-3.23},{"date":"2025-06-12","pct":-3.66},{"date":"2025-06-13","pct":-4.33},{"date":"2025-06-16","pct":-3.73},{"date":"2025-06-17","pct":-3.31},{"date":"2025-06-18","pct":-2.87},{"date":"2025-06-19","pct":-3.15},{"date":"2025-06-20","pct":-2.98},{"date":"2025-06-23","pct":-2.31},{"date":"2025-06-24","pct":-2.5},{"date":"2025-06-25","pct":-3.15},{"date":"2025-06-26","pct":-3.19},{"date":"2025-06-27","pct":-3.33},{"date":"2025-06-30","pct":-3.45},{"date":"2025-07-01","pct":-3.93},{"date":"2025-07-02","pct":-4.19},{"date":"2025-07-03","pct":-4.11},{"date":"2025-07-04","pct":-3.34},{"date":"2025-07-07","pct":-3.46},{"date":"2025-07-08","pct":-2.53},{"date":"2025-07-09","pct":-1.89},{"date":"2025-07-10","pct":-2.38},{"date":"2025-07-11","pct":-2.26},{"date":"2025-07-14","pct":-1.59},{"date":"2025-07-15","pct":-1.26},{"date":"2025-07-16","pct":-0.61},{"date":"2025-07-17","pct":-1.12},{"date":"2025-07-18","pct":-0.83},{"date":"2025-07-21","pct":-0.83},{"date":"2025-07-22","pct":-1.52},{"date":"2025-07-23","pct":-1.93},{"date":"2025-07-24","pct":-2.22},{"date":"2025-07-25","pct":-1.79},{"date":"2025-07-28","pct":-1.25},{"date":"2025-07-29","pct":-0.8},{"date":"2025-07-30","pct":-0.83},{"date":"2025-07-31","pct":-0.3},{"date":"2025-08-01","pct":0.73},{"date":"2025-08-04","pct":-1.56},{"date":"2025-08-05","pct":-1.93},{"date":"2025-08-06","pct":-1.41},{"date":"2025-08-07","pct":-1.66},{"date":"2025-08-08","pct":-1.9},{"date":"2025-08-11","pct":-1.34},{"date":"2025-08-12","pct":-1.04},{"date":"2025-08-13","pct":-1.28},{"date":"2025-08-14","pct":-1.71},{"date":"2025-08-15","pct":-1.33},{"date":"2025-08-18","pct":-1.61},{"date":"2025-08-19","pct":-1.18},{"date":"2025-08-20","pct":-1.3},{"date":"2025-08-21","pct":-1.58},{"date":"2025-08-22","pct":-0.86},{"date":"2025-08-25","pct":-1.64},{"date":"2025-08-26","pct":-1.24},{"date":"2025-08-27","pct":-1.48},{"date":"2025-08-28","pct":-1.58},{"date":"2025-08-29","pct":-1.93},{"date":"2025-09-01","pct":-1.72},{"date":"2025-09-02","pct":-1.73},{"date":"2025-09-03","pct":-0.75},{"date":"2025-09-04","pct":-1.13},{"date":"2025-09-05","pct":-0.87},{"date":"2025-09-08","pct":-0.89},{"date":"2025-09-09","pct":-1.55},{"date":"2025-09-10","pct":-1.53},{"date":"2025-09-11","pct":-1.57},{"date":"2025-09-12","pct":-1.64},{"date":"2025-09-15","pct":-1.34},{"date":"2025-09-16","pct":-1.52},{"date":"2025-09-17","pct":-2.18},{"date":"2025-09-18","pct":-1.86},{"date":"2025-09-19","pct":-1.16},{"date":"2025-09-22","pct":-1.06},{"date":"2025-09-23","pct":-1.3},{"date":"2025-09-24","pct":-1.38},{"date":"2025-09-25","pct":-0.62},{"date":"2025-09-26","pct":0.12},{"date":"2025-09-29","pct":-0.18},{"date":"2025-09-30","pct":-0.72},{"date":"2025-10-01","pct":-1.12},{"date":"2025-10-02","pct":-1.73},{"date":"2025-10-03","pct":-1.69},{"date":"2025-10-06","pct":-0.05},{"date":"2025-10-07","pct":0.44},{"date":"2025-10-08","pct":1.59},{"date":"2025-10-09","pct":2.01},{"date":"2025-10-10","pct":2.2},{"date":"2025-10-13","pct":1.59},{"date":"2025-10-14","pct":1.84},{"date":"2025-10-15","pct":1.37},{"date":"2025-10-16","pct":0.87},{"date":"2025-10-17","pct":0.3},{"date":"2025-10-20","pct":0.82},{"date":"2025-10-21","pct":0.73},{"date":"2025-10-22","pct":1.48},{"date":"2025-10-23","pct":1.52},{"date":"2025-10-24","pct":1.95},{"date":"2025-10-27","pct":2.26},{"date":"2025-10-28","pct":2.01},{"date":"2025-10-29","pct":1.37},{"date":"2025-10-30","pct":2.03},{"date":"2025-10-31","pct":2.82},{"date":"2025-11-03","pct":3.02},{"date":"2025-11-04","pct":3.02},{"date":"2025-11-05","pct":2.59},{"date":"2025-11-06","pct":2.94},{"date":"2025-11-07","pct":2.19},{"date":"2025-11-10","pct":2.77},{"date":"2025-11-11","pct":2.99},{"date":"2025-11-12","pct":2.94},{"date":"2025-11-13","pct":3.36},{"date":"2025-11-14","pct":3.31},{"date":"2025-11-17","pct":3.28},{"date":"2025-11-18","pct":3.74},{"date":"2025-11-19","pct":3.92},{"date":"2025-11-20","pct":4.89},{"date":"2025-11-21","pct":5.14},{"date":"2025-11-24","pct":4.68},{"date":"2025-11-25","pct":4.85},{"date":"2025-11-26","pct":4.38},{"date":"2025-11-27","pct":4.38},{"date":"2025-11-28","pct":4.41},{"date":"2025-12-01","pct":4.18},{"date":"2025-12-02","pct":3.93},{"date":"2025-12-03","pct":4.1},{"date":"2025-12-04","pct":3.63},{"date":"2025-12-05","pct":3.65},{"date":"2025-12-08","pct":3.78},{"date":"2025-12-09","pct":4.12},{"date":"2025-12-10","pct":4.78},{"date":"2025-12-11","pct":4.08},{"date":"2025-12-12","pct":3.94},{"date":"2025-12-15","pct":4.15},{"date":"2025-12-16","pct":3.57},{"date":"2025-12-17","pct":3.41},{"date":"2025-12-18","pct":3.89},{"date":"2025-12-19","pct":3.95},{"date":"2025-12-22","pct":5.34},{"date":"2025-12-23","pct":4.81},{"date":"2025-12-24","pct":4.34},{"date":"2025-12-25","pct":4.29},{"date":"2025-12-26","pct":4.28},{"date":"2025-12-29","pct":4.53},{"date":"2025-12-30","pct":4.23},{"date":"2025-12-31","pct":4.5},{"date":"2026-01-01","pct":4.72},{"date":"2026-01-02","pct":4.71},{"date":"2026-01-05","pct":4.89},{"date":"2026-01-06","pct":4.64},{"date":"2026-01-07","pct":4.68},{"date":"2026-01-08","pct":4.71},{"date":"2026-01-09","pct":4.81},{"date":"2026-01-12","pct":5.66},{"date":"2026-01-13","pct":5.55},{"date":"2026-01-14","pct":6.35},{"date":"2026-01-15","pct":5.83},{"date":"2026-01-16","pct":5.96},{"date":"2026-01-19","pct":5.25},{"date":"2026-01-20","pct":5.68},{"date":"2026-01-21","pct":5.67},{"date":"2026-01-22","pct":5.87},{"date":"2026-01-23","pct":5.9},{"date":"2026-01-26","pct":3.67},{"date":"2026-01-27","pct":3.11},{"date":"2026-01-28","pct":1.85},{"date":"2026-01-29","pct":2.28},{"date":"2026-01-30","pct":2.33},{"date":"2026-02-02","pct":3.69},{"date":"2026-02-03","pct":3.85},{"date":"2026-02-04","pct":4.09},{"date":"2026-02-05","pct":4.84},{"date":"2026-02-06","pct":4.75},{"date":"2026-02-09","pct":5.06},{"date":"2026-02-10","pct":4.31},{"date":"2026-02-11","pct":3.21},{"date":"2026-02-12","pct":2.4},{"date":"2026-02-13","pct":2.1},{"date":"2026-02-16","pct":2.07},{"date":"2026-02-17","pct":2.63},{"date":"2026-02-18","pct":2.32},{"date":"2026-02-19","pct":3.35},{"date":"2026-02-20","pct":3.66},{"date":"2026-02-23","pct":3.11},{"date":"2026-02-24","pct":3.31},{"date":"2026-02-25","pct":4.14},{"date":"2026-02-26","pct":4.36},{"date":"2026-02-27","pct":4.13},{"date":"2026-03-02","pct":4.65},{"date":"2026-03-03","pct":5.06},{"date":"2026-03-04","pct":5.41},{"date":"2026-03-05","pct":4.88},{"date":"2026-03-06","pct":5.25},{"date":"2026-03-09","pct":5.85},{"date":"2026-03-10","pct":5.46},{"date":"2026-03-11","pct":5.64},{"date":"2026-03-12","pct":6.28},{"date":"2026-03-13","pct":6.37},{"date":"2026-03-16","pct":6.61},{"date":"2026-03-17","pct":6.3},{"date":"2026-03-18","pct":6.15},{"date":"2026-03-19","pct":6.76},{"date":"2026-03-20","pct":5.51},{"date":"2026-03-23","pct":6.53}],"ナスダック":[{"date":"2025-03-24","pct":0.0},{"date":"2025-03-25","pct":0.46},{"date":"2025-03-26","pct":-1.59},{"date":"2025-03-27","pct":-2.11},{"date":"2025-03-28","pct":-4.76},{"date":"2025-03-31","pct":-4.89},{"date":"2025-04-01","pct":-4.06},{"date":"2025-04-02","pct":-3.23},{"date":"2025-04-03","pct":-9.01},{"date":"2025-04-04","pct":-14.3},{"date":"2025-04-07","pct":-14.21},{"date":"2025-04-08","pct":-16.06},{"date":"2025-04-09","pct":-5.85},{"date":"2025-04-10","pct":-9.9},{"date":"2025-04-11","pct":-8.05},{"date":"2025-04-14","pct":-7.46},{"date":"2025-04-15","pct":-7.51},{"date":"2025-04-16","pct":-10.34},{"date":"2025-04-17","pct":-10.46},{"date":"2025-04-21","pct":-12.74},{"date":"2025-04-22","pct":-10.38},{"date":"2025-04-23","pct":-8.14},{"date":"2025-04-24","pct":-5.62},{"date":"2025-04-25","pct":-4.43},{"date":"2025-04-28","pct":-4.52},{"date":"2025-04-29","pct":-4.0},{"date":"2025-04-30","pct":-4.08},{"date":"2025-05-01","pct":-2.63},{"date":"2025-05-02","pct":-1.16},{"date":"2025-05-05","pct":-1.89},{"date":"2025-05-06","pct":-2.74},{"date":"2025-05-07","pct":-2.48},{"date":"2025-05-08","pct":-1.43},{"date":"2025-05-09","pct":-1.43},{"date":"2025-05-12","pct":2.86},{"date":"2025-05-13","pct":4.52},{"date":"2025-05-14","pct":5.27},{"date":"2025-05-15","pct":5.08},{"date":"2025-05-16","pct":5.62},{"date":"2025-05-19","pct":5.65},{"date":"2025-05-20","pct":5.25},{"date":"2025-05-21","pct":3.76},{"date":"2025-05-22","pct":4.05},{"date":"2025-05-23","pct":3.02},{"date":"2025-05-27","pct":5.56},{"date":"2025-05-28","pct":5.02},{"date":"2025-05-29","pct":5.43},{"date":"2025-05-30","pct":5.09},{"date":"2025-06-02","pct":5.79},{"date":"2025-06-03","pct":6.65},{"date":"2025-06-04","pct":6.99},{"date":"2025-06-05","pct":6.1},{"date":"2025-06-06","pct":7.37},{"date":"2025-06-09","pct":7.71},{"date":"2025-06-10","pct":8.39},{"date":"2025-06-11","pct":7.85},{"date":"2025-06-12","pct":8.1},{"date":"2025-06-13","pct":6.7},{"date":"2025-06-16","pct":8.32},{"date":"2025-06-17","pct":7.33},{"date":"2025-06-18","pct":7.46},{"date":"2025-06-20","pct":6.92},{"date":"2025-06-23","pct":7.93},{"date":"2025-06-24","pct":9.48},{"date":"2025-06-25","pct":9.81},{"date":"2025-06-26","pct":10.88},{"date":"2025-06-27","pct":11.46},{"date":"2025-06-30","pct":11.99},{"date":"2025-07-01","pct":11.07},{"date":"2025-07-02","pct":12.12},{"date":"2025-07-03","pct":13.26},{"date":"2025-07-07","pct":12.23},{"date":"2025-07-08","pct":12.26},{"date":"2025-07-09","pct":13.32},{"date":"2025-07-10","pct":13.43},{"date":"2025-07-11","pct":13.18},{"date":"2025-07-14","pct":13.48},{"date":"2025-07-15","pct":13.69},{"date":"2025-07-16","pct":13.98},{"date":"2025-07-17","pct":14.83},{"date":"2025-07-18","pct":14.88},{"date":"2025-07-21","pct":15.32},{"date":"2025-07-22","pct":14.87},{"date":"2025-07-23","pct":15.57},{"date":"2025-07-24","pct":15.78},{"date":"2025-07-25","pct":16.05},{"date":"2025-07-28","pct":16.44},{"date":"2025-07-29","pct":16.0},{"date":"2025-07-30","pct":16.17},{"date":"2025-07-31","pct":16.13},{"date":"2025-08-01","pct":13.53},{"date":"2025-08-04","pct":15.75},{"date":"2025-08-05","pct":15.0},{"date":"2025-08-06","pct":16.39},{"date":"2025-08-07","pct":16.79},{"date":"2025-08-08","pct":17.93},{"date":"2025-08-11","pct":17.58},{"date":"2025-08-12","pct":19.21},{"date":"2025-08-13","pct":19.38},{"date":"2025-08-14","pct":19.36},{"date":"2025-08-15","pct":18.88},{"date":"2025-08-18","pct":18.92},{"date":"2025-08-19","pct":17.19},{"date":"2025-08-20","pct":16.41},{"date":"2025-08-21","pct":16.01},{"date":"2025-08-22","pct":18.19},{"date":"2025-08-25","pct":17.93},{"date":"2025-08-26","pct":18.45},{"date":"2025-08-27","pct":18.7},{"date":"2025-08-28","pct":19.33},{"date":"2025-08-29","pct":17.96},{"date":"2025-09-02","pct":16.99},{"date":"2025-09-03","pct":18.19},{"date":"2025-09-04","pct":19.35},{"date":"2025-09-05","pct":19.31},{"date":"2025-09-08","pct":19.85},{"date":"2025-09-09","pct":20.29},{"date":"2025-09-10","pct":20.33},{"date":"2025-09-11","pct":21.19},{"date":"2025-09-12","pct":21.73},{"date":"2025-09-15","pct":22.87},{"date":"2025-09-16","pct":22.79},{"date":"2025-09-17","pct":22.39},{"date":"2025-09-18","pct":23.54},{"date":"2025-09-19","pct":24.43},{"date":"2025-09-22","pct":25.29},{"date":"2025-09-23","pct":24.11},{"date":"2025-09-24","pct":23.69},{"date":"2025-09-25","pct":23.07},{"date":"2025-09-26","pct":23.62},{"date":"2025-09-29","pct":24.21},{"date":"2025-09-30","pct":24.58},{"date":"2025-10-01","pct":25.11},{"date":"2025-10-02","pct":25.6},{"date":"2025-10-03","pct":25.25},{"date":"2025-10-06","pct":26.13},{"date":"2025-10-07","pct":25.29},{"date":"2025-10-08","pct":26.69},{"date":"2025-10-09","pct":26.59},{"date":"2025-10-10","pct":22.08},{"date":"2025-10-13","pct":24.77},{"date":"2025-10-14","pct":23.82},{"date":"2025-10-15","pct":24.64},{"date":"2025-10-16","pct":24.05},{"date":"2025-10-17","pct":24.69},{"date":"2025-10-20","pct":26.4},{"date":"2025-10-21","pct":26.2},{"date":"2025-10-22","pct":25.03},{"date":"2025-10-23","pct":26.13},{"date":"2025-10-24","pct":27.58},{"date":"2025-10-27","pct":29.96},{"date":"2025-10-28","pct":31.0},{"date":"2025-10-29","pct":31.72},{"date":"2025-10-30","pct":29.65},{"date":"2025-10-31","pct":30.44},{"date":"2025-11-03","pct":31.04},{"date":"2025-11-04","pct":28.37},{"date":"2025-11-05","pct":29.2},{"date":"2025-11-06","pct":26.75},{"date":"2025-11-07","pct":26.48},{"date":"2025-11-10","pct":29.35},{"date":"2025-11-11","pct":29.03},{"date":"2025-11-12","pct":28.69},{"date":"2025-11-13","pct":25.74},{"date":"2025-11-14","pct":25.91},{"date":"2025-11-17","pct":24.85},{"date":"2025-11-18","pct":23.33},{"date":"2025-11-19","pct":24.06},{"date":"2025-11-20","pct":21.38},{"date":"2025-11-21","pct":22.46},{"date":"2025-11-24","pct":25.75},{"date":"2025-11-25","pct":26.59},{"date":"2025-11-26","pct":27.63},{"date":"2025-11-28","pct":28.46},{"date":"2025-12-01","pct":27.97},{"date":"2025-12-02","pct":28.73},{"date":"2025-12-03","pct":28.95},{"date":"2025-12-04","pct":29.23},{"date":"2025-12-05","pct":29.63},{"date":"2025-12-08","pct":29.45},{"date":"2025-12-09","pct":29.62},{"date":"2025-12-10","pct":30.05},{"date":"2025-12-11","pct":29.72},{"date":"2025-12-12","pct":27.53},{"date":"2025-12-15","pct":26.77},{"date":"2025-12-16","pct":27.07},{"date":"2025-12-17","pct":24.77},{"date":"2025-12-18","pct":26.49},{"date":"2025-12-19","pct":28.14},{"date":"2025-12-22","pct":28.81},{"date":"2025-12-23","pct":29.54},{"date":"2025-12-24","pct":29.82},{"date":"2025-12-26","pct":29.71},{"date":"2025-12-29","pct":29.06},{"date":"2025-12-30","pct":28.76},{"date":"2025-12-31","pct":27.78},{"date":"2026-01-02","pct":27.75},{"date":"2026-01-05","pct":28.63},{"date":"2026-01-06","pct":29.46},{"date":"2026-01-07","pct":29.67},{"date":"2026-01-08","pct":29.09},{"date":"2026-01-09","pct":30.14},{"date":"2026-01-12","pct":30.49},{"date":"2026-01-13","pct":30.36},{"date":"2026-01-14","pct":29.05},{"date":"2026-01-15","pct":29.37},{"date":"2026-01-16","pct":29.29},{"date":"2026-01-20","pct":26.2},{"date":"2026-01-21","pct":27.69},{"date":"2026-01-22","pct":28.85},{"date":"2026-01-23","pct":29.21},{"date":"2026-01-26","pct":29.76},{"date":"2026-01-27","pct":30.95},{"date":"2026-01-28","pct":31.17},{"date":"2026-01-29","pct":30.22},{"date":"2026-01-30","pct":28.99},{"date":"2026-02-02","pct":29.71},{"date":"2026-02-03","pct":27.86},{"date":"2026-02-04","pct":25.93},{"date":"2026-02-05","pct":23.93},{"date":"2026-02-06","pct":26.62},{"date":"2026-02-09","pct":27.77},{"date":"2026-02-10","pct":27.02},{"date":"2026-02-11","pct":26.82},{"date":"2026-02-12","pct":24.24},{"date":"2026-02-13","pct":23.96},{"date":"2026-02-17","pct":24.13},{"date":"2026-02-18","pct":25.1},{"date":"2026-02-19","pct":24.71},{"date":"2026-02-20","pct":25.83},{"date":"2026-02-23","pct":24.4},{"date":"2026-02-24","pct":25.7},{"date":"2026-02-25","pct":27.29},{"date":"2026-02-26","pct":25.78},{"date":"2026-02-27","pct":24.63},{"date":"2026-03-02","pct":25.07},{"date":"2026-03-03","pct":23.8},{"date":"2026-03-04","pct":25.39},{"date":"2026-03-05","pct":25.07},{"date":"2026-03-06","pct":23.09},{"date":"2026-03-09","pct":24.78},{"date":"2026-03-10","pct":24.79},{"date":"2026-03-11","pct":24.89},{"date":"2026-03-12","pct":22.67},{"date":"2026-03-13","pct":21.53},{"date":"2026-03-16","pct":23.01},{"date":"2026-03-17","pct":23.59},{"date":"2026-03-18","pct":21.79},{"date":"2026-03-19","pct":21.45},{"date":"2026-03-20","pct":19.02}],"VIX":[{"date":"2025-03-24","pct":0.0},{"date":"2025-03-25","pct":-1.89},{"date":"2025-03-26","pct":4.86},{"date":"2025-03-27","pct":6.92},{"date":"2025-03-28","pct":23.86},{"date":"2025-03-31","pct":27.46},{"date":"2025-04-01","pct":24.54},{"date":"2025-04-02","pct":23.05},{"date":"2025-04-03","pct":71.74},{"date":"2025-04-04","pct":159.21},{"date":"2025-04-07","pct":168.76},{"date":"2025-04-08","pct":199.37},{"date":"2025-04-09","pct":92.33},{"date":"2025-04-10","pct":132.95},{"date":"2025-04-11","pct":114.87},{"date":"2025-04-14","pct":76.72},{"date":"2025-04-15","pct":72.31},{"date":"2025-04-16","pct":86.73},{"date":"2025-04-17","pct":69.62},{"date":"2025-04-21","pct":93.48},{"date":"2025-04-22","pct":74.89},{"date":"2025-04-23","pct":62.76},{"date":"2025-04-24","pct":51.43},{"date":"2025-04-25","pct":42.11},{"date":"2025-04-28","pct":43.88},{"date":"2025-04-29","pct":38.27},{"date":"2025-04-30","pct":41.3},{"date":"2025-05-01","pct":40.73},{"date":"2025-05-02","pct":29.75},{"date":"2025-05-05","pct":35.24},{"date":"2025-05-06","pct":41.65},{"date":"2025-05-07","pct":34.73},{"date":"2025-05-08","pct":28.6},{"date":"2025-05-09","pct":25.29},{"date":"2025-05-12","pct":5.21},{"date":"2025-05-13","pct":4.23},{"date":"2025-05-14","pct":6.52},{"date":"2025-05-15","pct":2.0},{"date":"2025-05-16","pct":-1.37},{"date":"2025-05-19","pct":3.78},{"date":"2025-05-20","pct":3.49},{"date":"2025-05-21","pct":19.39},{"date":"2025-05-22","pct":16.02},{"date":"2025-05-23","pct":27.52},{"date":"2025-05-26","pct":17.68},{"date":"2025-05-27","pct":8.47},{"date":"2025-05-28","pct":10.47},{"date":"2025-05-29","pct":9.73},{"date":"2025-05-30","pct":6.24},{"date":"2025-06-02","pct":5.03},{"date":"2025-06-03","pct":1.2},{"date":"2025-06-04","pct":0.74},{"date":"2025-06-05","pct":5.72},{"date":"2025-06-06","pct":-4.06},{"date":"2025-06-09","pct":-1.83},{"date":"2025-06-10","pct":-3.03},{"date":"2025-06-11","pct":-1.26},{"date":"2025-06-12","pct":3.09},{"date":"2025-06-13","pct":19.11},{"date":"2025-06-16","pct":9.32},{"date":"2025-06-17","pct":23.57},{"date":"2025-06-18","pct":15.22},{"date":"2025-06-19","pct":26.83},{"date":"2025-06-20","pct":17.96},{"date":"2025-06-23","pct":13.44},{"date":"2025-06-24","pct":0.0},{"date":"2025-06-25","pct":-4.12},{"date":"2025-06-26","pct":-5.09},{"date":"2025-06-27","pct":-6.64},{"date":"2025-06-30","pct":-4.29},{"date":"2025-07-01","pct":-3.72},{"date":"2025-07-02","pct":-4.81},{"date":"2025-07-03","pct":-6.29},{"date":"2025-07-04","pct":0.0},{"date":"2025-07-07","pct":1.77},{"date":"2025-07-08","pct":-3.83},{"date":"2025-07-09","pct":-8.81},{"date":"2025-07-10","pct":-9.73},{"date":"2025-07-11","pct":-6.18},{"date":"2025-07-14","pct":-1.6},{"date":"2025-07-15","pct":-0.57},{"date":"2025-07-16","pct":-1.83},{"date":"2025-07-17","pct":-5.49},{"date":"2025-07-18","pct":-6.12},{"date":"2025-07-21","pct":-4.75},{"date":"2025-07-22","pct":-5.61},{"date":"2025-07-23","pct":-12.07},{"date":"2025-07-24","pct":-11.96},{"date":"2025-07-25","pct":-14.59},{"date":"2025-07-28","pct":-14.02},{"date":"2025-07-29","pct":-8.58},{"date":"2025-07-30","pct":-11.44},{"date":"2025-07-31","pct":-4.35},{"date":"2025-08-01","pct":16.59},{"date":"2025-08-04","pct":0.23},{"date":"2025-08-05","pct":2.12},{"date":"2025-08-06","pct":-4.06},{"date":"2025-08-07","pct":-5.21},{"date":"2025-08-08","pct":-13.33},{"date":"2025-08-11","pct":-7.04},{"date":"2025-08-12","pct":-15.73},{"date":"2025-08-13","pct":-17.11},{"date":"2025-08-14","pct":-15.16},{"date":"2025-08-15","pct":-13.67},{"date":"2025-08-18","pct":-14.24},{"date":"2025-08-19","pct":-10.93},{"date":"2025-08-20","pct":-10.24},{"date":"2025-08-21","pct":-5.03},{"date":"2025-08-22","pct":-18.65},{"date":"2025-08-25","pct":-15.39},{"date":"2025-08-26","pct":-16.36},{"date":"2025-08-27","pct":-15.05},{"date":"2025-08-28","pct":-17.45},{"date":"2025-08-29","pct":-12.13},{"date":"2025-09-01","pct":-7.78},{"date":"2025-09-02","pct":-1.77},{"date":"2025-09-03","pct":-6.46},{"date":"2025-09-04","pct":-12.47},{"date":"2025-09-05","pct":-13.16},{"date":"2025-09-08","pct":-13.56},{"date":"2025-09-09","pct":-13.96},{"date":"2025-09-10","pct":-12.19},{"date":"2025-09-11","pct":-15.85},{"date":"2025-09-12","pct":-15.56},{"date":"2025-09-15","pct":-10.24},{"date":"2025-09-16","pct":-6.41},{"date":"2025-09-17","pct":-10.07},{"date":"2025-09-18","pct":-10.18},{"date":"2025-09-19","pct":-11.61},{"date":"2025-09-22","pct":-7.89},{"date":"2025-09-23","pct":-4.81},{"date":"2025-09-24","pct":-7.44},{"date":"2025-09-25","pct":-4.23},{"date":"2025-09-26","pct":-12.53},{"date":"2025-09-29","pct":-7.78},{"date":"2025-09-30","pct":-6.86},{"date":"2025-10-01","pct":-6.81},{"date":"2025-10-02","pct":-4.86},{"date":"2025-10-03","pct":-4.75},{"date":"2025-10-06","pct":-6.35},{"date":"2025-10-07","pct":-1.37},{"date":"2025-10-08","pct":-6.75},{"date":"2025-10-09","pct":-6.01},{"date":"2025-10-10","pct":23.91},{"date":"2025-10-13","pct":8.87},{"date":"2025-10-14","pct":19.05},{"date":"2025-10-15","pct":18.08},{"date":"2025-10-16","pct":44.79},{"date":"2025-10-17","pct":18.88},{"date":"2025-10-20","pct":4.29},{"date":"2025-10-21","pct":2.23},{"date":"2025-10-22","pct":6.41},{"date":"2025-10-23","pct":-1.03},{"date":"2025-10-24","pct":-6.35},{"date":"2025-10-27","pct":-9.67},{"date":"2025-10-28","pct":-6.06},{"date":"2025-10-29","pct":-3.2},{"date":"2025-10-30","pct":-3.26},{"date":"2025-10-31","pct":-0.23},{"date":"2025-11-03","pct":-1.77},{"date":"2025-11-04","pct":8.7},{"date":"2025-11-05","pct":3.03},{"date":"2025-11-06","pct":11.56},{"date":"2025-11-07","pct":9.15},{"date":"2025-11-10","pct":0.69},{"date":"2025-11-11","pct":-1.14},{"date":"2025-11-12","pct":0.17},{"date":"2025-11-13","pct":14.42},{"date":"2025-11-14","pct":13.44},{"date":"2025-11-17","pct":28.03},{"date":"2025-11-18","pct":41.25},{"date":"2025-11-19","pct":35.35},{"date":"2025-11-20","pct":51.14},{"date":"2025-11-21","pct":34.04},{"date":"2025-11-24","pct":17.39},{"date":"2025-11-25","pct":6.18},{"date":"2025-11-26","pct":-1.66},{"date":"2025-11-27","pct":-1.54},{"date":"2025-11-28","pct":-6.46},{"date":"2025-12-01","pct":-1.37},{"date":"2025-12-02","pct":-5.09},{"date":"2025-12-03","pct":-8.01},{"date":"2025-12-04","pct":-9.73},{"date":"2025-12-05","pct":-11.84},{"date":"2025-12-08","pct":-4.69},{"date":"2025-12-09","pct":-3.15},{"date":"2025-12-10","pct":-9.78},{"date":"2025-12-11","pct":-15.05},{"date":"2025-12-12","pct":-9.95},{"date":"2025-12-15","pct":-5.61},{"date":"2025-12-16","pct":-5.72},{"date":"2025-12-17","pct":0.8},{"date":"2025-12-18","pct":-3.49},{"date":"2025-12-19","pct":-14.7},{"date":"2025-12-22","pct":-19.45},{"date":"2025-12-23","pct":-19.91},{"date":"2025-12-24","pct":-22.94},{"date":"2025-12-26","pct":-22.2},{"date":"2025-12-29","pct":-18.76},{"date":"2025-12-30","pct":-18.02},{"date":"2025-12-31","pct":-14.47},{"date":"2026-01-02","pct":-16.99},{"date":"2026-01-05","pct":-14.76},{"date":"2026-01-06","pct":-15.62},{"date":"2026-01-07","pct":-12.01},{"date":"2026-01-08","pct":-11.61},{"date":"2026-01-09","pct":-17.11},{"date":"2026-01-12","pct":-13.5},{"date":"2026-01-13","pct":-8.58},{"date":"2026-01-14","pct":-4.18},{"date":"2026-01-15","pct":-9.38},{"date":"2026-01-16","pct":-9.27},{"date":"2026-01-19","pct":7.78},{"date":"2026-01-20","pct":14.93},{"date":"2026-01-21","pct":-3.32},{"date":"2026-01-22","pct":-10.53},{"date":"2026-01-23","pct":-7.95},{"date":"2026-01-26","pct":-7.61},{"date":"2026-01-27","pct":-6.46},{"date":"2026-01-28","pct":-6.46},{"date":"2026-01-29","pct":-3.43},{"date":"2026-01-30","pct":-0.23},{"date":"2026-02-02","pct":-6.52},{"date":"2026-02-03","pct":2.97},{"date":"2026-02-04","pct":6.64},{"date":"2026-02-05","pct":24.54},{"date":"2026-02-06","pct":16.53},{"date":"2026-02-09","pct":-0.69},{"date":"2026-02-10","pct":1.77},{"date":"2026-02-11","pct":0.97},{"date":"2026-02-12","pct":19.11},{"date":"2026-02-13","pct":17.85},{"date":"2026-02-16","pct":21.28},{"date":"2026-02-17","pct":16.08},{"date":"2026-02-18","pct":12.24},{"date":"2026-02-19","pct":15.73},{"date":"2026-02-20","pct":9.21},{"date":"2026-02-23","pct":20.19},{"date":"2026-02-24","pct":11.84},{"date":"2026-02-25","pct":2.57},{"date":"2026-02-26","pct":6.58},{"date":"2026-02-27","pct":13.62},{"date":"2026-03-02","pct":22.65},{"date":"2026-03-03","pct":34.84},{"date":"2026-03-04","pct":21.0},{"date":"2026-03-05","pct":35.87},{"date":"2026-03-06","pct":68.71},{"date":"2026-03-09","pct":45.88},{"date":"2026-03-10","pct":42.62},{"date":"2026-03-11","pct":38.62},{"date":"2026-03-12","pct":56.12},{"date":"2026-03-13","pct":55.55},{"date":"2026-03-16","pct":34.5},{"date":"2026-03-17","pct":27.97},{"date":"2026-03-18","pct":43.54},{"date":"2026-03-19","pct":37.64},{"date":"2026-03-20","pct":53.2}]},"updated_at":"2026/03/23 12:34 JST"},"heatmap":{"data":{"半導体":{"1W":-3.91,"1M":-11.63,"3M":13.85,"6M":26.39,"1Y":78.09},"AI・クラウド":{"1W":-2.27,"1M":5.76,"3M":-20.19,"6M":-15.46,"1Y":-0.83},"EV・電気自動車":{"1W":-4.99,"1M":-13.91,"3M":-4.35,"6M":5.38,"1Y":12.53},"ゲーム・エンタメ":{"1W":-3.38,"1M":5.23,"3M":-6.36,"6M":-15.95,"1Y":-8.79},"銀行・金融":{"1W":-1.3,"1M":-11.69,"3M":3.01,"6M":17.24,"1Y":31.08},"地方銀行":{"1W":-2.88,"1M":-13.55,"3M":13.36,"6M":34.91,"1Y":49.81},"保険":{"1W":-2.8,"1M":-7.49,"3M":3.7,"6M":11.71,"1Y":17.65},"不動産":{"1W":-7.03,"1M":-11.32,"3M":8.11,"6M":18.4,"1Y":36.52},"医薬品・バイオ":{"1W":-4.66,"1M":-8.09,"3M":5.79,"6M":16.11,"1Y":25.55},"ヘルスケア・介護":{"1W":-1.41,"1M":-0.19,"3M":-12.41,"6M":-13.99,"1Y":-10.7},"食品・飲料":{"1W":-4.72,"1M":-8.49,"3M":4.62,"6M":3.54,"1Y":7.09},"小売・EC":{"1W":-3.62,"1M":-9.86,"3M":-8.16,"6M":2.77,"1Y":11.3},"通信":{"1W":-1.22,"1M":-0.43,"3M":-6.92,"6M":-4.0,"1Y":2.75},"鉄鋼・素材":{"1W":-3.99,"1M":-15.22,"3M":4.29,"6M":25.98,"1Y":38.6},"化学":{"1W":-4.97,"1M":-12.23,"3M":1.86,"6M":4.96,"1Y":19.6},"建設・インフラ":{"1W":-6.29,"1M":-15.59,"3M":3.36,"6M":33.8,"1Y":81.75},"輸送・物流":{"1W":-2.43,"1M":4.57,"3M":11.88,"6M":8.02,"1Y":9.57},"防衛・航空宇宙":{"1W":-6.24,"1M":-7.46,"3M":13.08,"6M":26.39,"1Y":71.79},"フィンテック":{"1W":-0.89,"1M":6.34,"3M":-27.28,"6M":-35.98,"1Y":-18.2},"再生可能エネルギー":{"1W":-3.51,"1M":0.38,"3M":21.99,"6M":21.7,"1Y":50.3},"ロボット・自動化":{"1W":-4.94,"1M":-13.48,"3M":4.46,"6M":19.34,"1Y":19.34},"レアアース・資源":{"1W":-8.63,"1M":-18.96,"3M":26.51,"6M":87.87,"1Y":108.23},"サイバーセキュリティ":{"1W":-9.54,"1M":-4.1,"3M":-7.62,"6M":-14.59,"1Y":31.08},"ドローン":{"1W":-13.86,"1M":13.18,"3M":60.66,"6M":35.21,"1Y":25.07},"造船":{"1W":-4.09,"1M":-19.16,"3M":15.6,"6M":35.7,"1Y":155.51},"観光・ホテル・レジャー":{"1W":-1.52,"1M":-8.98,"3M":-5.18,"6M":-10.68,"1Y":-0.82},"農業・フードテック":{"1W":-4.79,"1M":-15.18,"3M":5.84,"6M":9.45,"1Y":17.16},"教育・HR・人材":{"1W":-4.93,"1M":-0.52,"3M":-29.09,"6M":-25.74,"1Y":-27.3},"脱炭素・ESG":{"1W":-2.44,"1M":-10.28,"3M":2.72,"6M":16.19,"1Y":36.77},"宇宙・衛星":{"1W":-6.07,"1M":-6.65,"3M":3.52,"6M":19.56,"1Y":78.31}},"updated_at":"2026/03/23 12:34 JST"},"theme_names":{"themes":["半導体","AI・クラウド","EV・電気自動車","ゲーム・エンタメ","銀行・金融","地方銀行","保険","不動産","医薬品・バイオ","ヘルスケア・介護","食品・飲料","小売・EC","通信","鉄鋼・素材","化学","建設・インフラ","輸送・物流","防衛・航空宇宙","フィンテック","再生可能エネルギー","ロボット・自動化","レアアース・資源","サイバーセキュリティ","ドローン","造船","観光・ホテル・レジャー","農業・フードテック","教育・HR・人材","脱炭素・ESG","宇宙・衛星"],"updated_at":"2026/03/23 12:34 JST"},"status":{"time":"12:34 JST","date":"2026/03/23","is_open":true,"label":"open","updated_at":"2026/03/23 12:34 JST"}}