{
  "secCode": "4980",
  "issuerName": "デクセリアルズ株式会社",
  "updated_at": "2026/07/04 18:53 JST",
  "latestDate": "2026-06-22",
  "latest": [
    {
      "rank": 1,
      "name": "日本マスタートラスト信託銀行株式会社（信託口）",
      "shares": 29696700,
      "ratio": 17.08,
      "category": "trust",
      "category_label": "信託口（国内機関・年金/投信）",
      "is_founder_family": false
    },
    {
      "rank": 2,
      "name": "ＳＴＡＴＥ　ＳＴＲＥＥＴ　ＢＡＮＫ　ＡＮＤ　ＴＲＵＳＴ　ＣＯＭＰＡＮＹ　５０５００１\n（常任代理人　株式会社みずほ銀行決済営業部）",
      "shares": 16906667,
      "ratio": 9.72,
      "category": "financial",
      "category_label": "銀行・保険",
      "is_founder_family": false
    },
    {
      "rank": 3,
      "name": "株式会社日本カストディ銀行（信託口）",
      "shares": 13324300,
      "ratio": 7.66,
      "category": "trust",
      "category_label": "信託口（国内機関・年金/投信）",
      "is_founder_family": false
    },
    {
      "rank": 4,
      "name": "株式会社日本カストディ銀行（信託Ｅ口）",
      "shares": 6376964,
      "ratio": 3.67,
      "category": "trust",
      "category_label": "信託口（国内機関・年金/投信）",
      "is_founder_family": false
    },
    {
      "rank": 5,
      "name": "野村信託銀行株式会社（投信口）",
      "shares": 6267100,
      "ratio": 3.6,
      "category": "trust",
      "category_label": "信託口（国内機関・年金/投信）",
      "is_founder_family": false
    },
    {
      "rank": 6,
      "name": "大日本印刷株式会社",
      "shares": 4687500,
      "ratio": 2.7,
      "category": "corporate",
      "category_label": "事業法人",
      "is_founder_family": false
    },
    {
      "rank": 7,
      "name": "ＳＴＡＴＥ　ＳＴＲＥＥＴ　ＢＡＮＫ　ＡＮＤ　ＴＲＵＳＴ　ＣＯＭＰＡＮＹ　５０５１０３\n（常任代理人　株式会社みずほ銀行決済営業部）",
      "shares": 2484399,
      "ratio": 1.43,
      "category": "financial",
      "category_label": "銀行・保険",
      "is_founder_family": false
    },
    {
      "rank": 8,
      "name": "ＪＰ　ＭＯＲＧＡＮ　ＣＨＡＳＥ　ＢＡＮＫ　３８５７８１\n（常任代理人　株式会社みずほ銀行決済営業部）",
      "shares": 2352528,
      "ratio": 1.35,
      "category": "financial",
      "category_label": "銀行・保険",
      "is_founder_family": false
    },
    {
      "rank": 9,
      "name": "ＭＩＳＡＫＩ　ＥＮＧＡＧＥＭＥＮＴ　ＭＡＳＴＥＲ　ＦＵＮＤ\n（常任代理人　香港上海銀行東京支店セキュリティーズ・サービシズ・オペレーションズ）",
      "shares": 2288500,
      "ratio": 1.32,
      "category": "financial",
      "category_label": "銀行・保険",
      "is_founder_family": false
    },
    {
      "rank": 10,
      "name": "ＢＮＰ　ＰＡＲＩＢＡＳ　ＰＡＲＩＳ／２Ｓ／ＪＡＳＤＥＣ／ＣＤＣ　ＡＶＯＩＲＳ　ＣＬＩＥＮＴＳ　ＡＩＦＭ\n（常任代理人　香港上海銀行東京支店セキュリティーズ・サービシズ・オペレーションズ）",
      "shares": 2127000,
      "ratio": 1.22,
      "category": "financial",
      "category_label": "銀行・保険",
      "is_founder_family": false
    }
  ],
  "latestSummary": {
    "by_category": {
      "trust": 32.01,
      "financial": 15.04,
      "corporate": 2.7
    },
    "individual_total": 0,
    "top10_total": 49.75
  },
  "history": [
    {
      "submitDate": "2026-06-22",
      "docType": "120",
      "docTypeName": "有価証券報告書－第14期(2025/04/01－2026/03/31)",
      "docID": "S100YGAR",
      "shareholders": [
        {
          "rank": 1,
          "name": "日本マスタートラスト信託銀行株式会社（信託口）",
          "shares": 29696700,
          "ratio": 17.08,
          "category": "trust",
          "category_label": "信託口（国内機関・年金/投信）",
          "is_founder_family": false
        },
        {
          "rank": 2,
          "name": "ＳＴＡＴＥ　ＳＴＲＥＥＴ　ＢＡＮＫ　ＡＮＤ　ＴＲＵＳＴ　ＣＯＭＰＡＮＹ　５０５００１\n（常任代理人　株式会社みずほ銀行決済営業部）",
          "shares": 16906667,
          "ratio": 9.72,
          "category": "financial",
          "category_label": "銀行・保険",
          "is_founder_family": false
        },
        {
          "rank": 3,
          "name": "株式会社日本カストディ銀行（信託口）",
          "shares": 13324300,
          "ratio": 7.66,
          "category": "trust",
          "category_label": "信託口（国内機関・年金/投信）",
          "is_founder_family": false
        },
        {
          "rank": 4,
          "name": "株式会社日本カストディ銀行（信託Ｅ口）",
          "shares": 6376964,
          "ratio": 3.67,
          "category": "trust",
          "category_label": "信託口（国内機関・年金/投信）",
          "is_founder_family": false
        },
        {
          "rank": 5,
          "name": "野村信託銀行株式会社（投信口）",
          "shares": 6267100,
          "ratio": 3.6,
          "category": "trust",
          "category_label": "信託口（国内機関・年金/投信）",
          "is_founder_family": false
        },
        {
          "rank": 6,
          "name": "大日本印刷株式会社",
          "shares": 4687500,
          "ratio": 2.7,
          "category": "corporate",
          "category_label": "事業法人",
          "is_founder_family": false
        },
        {
          "rank": 7,
          "name": "ＳＴＡＴＥ　ＳＴＲＥＥＴ　ＢＡＮＫ　ＡＮＤ　ＴＲＵＳＴ　ＣＯＭＰＡＮＹ　５０５１０３\n（常任代理人　株式会社みずほ銀行決済営業部）",
          "shares": 2484399,
          "ratio": 1.43,
          "category": "financial",
          "category_label": "銀行・保険",
          "is_founder_family": false
        },
        {
          "rank": 8,
          "name": "ＪＰ　ＭＯＲＧＡＮ　ＣＨＡＳＥ　ＢＡＮＫ　３８５７８１\n（常任代理人　株式会社みずほ銀行決済営業部）",
          "shares": 2352528,
          "ratio": 1.35,
          "category": "financial",
          "category_label": "銀行・保険",
          "is_founder_family": false
        },
        {
          "rank": 9,
          "name": "ＭＩＳＡＫＩ　ＥＮＧＡＧＥＭＥＮＴ　ＭＡＳＴＥＲ　ＦＵＮＤ\n（常任代理人　香港上海銀行東京支店セキュリティーズ・サービシズ・オペレーションズ）",
          "shares": 2288500,
          "ratio": 1.32,
          "category": "financial",
          "category_label": "銀行・保険",
          "is_founder_family": false
        },
        {
          "rank": 10,
          "name": "ＢＮＰ　ＰＡＲＩＢＡＳ　ＰＡＲＩＳ／２Ｓ／ＪＡＳＤＥＣ／ＣＤＣ　ＡＶＯＩＲＳ　ＣＬＩＥＮＴＳ　ＡＩＦＭ\n（常任代理人　香港上海銀行東京支店セキュリティーズ・サービシズ・オペレーションズ）",
          "shares": 2127000,
          "ratio": 1.22,
          "category": "financial",
          "category_label": "銀行・保険",
          "is_founder_family": false
        }
      ],
      "summary": {
        "by_category": {
          "trust": 32.01,
          "financial": 15.04,
          "corporate": 2.7
        },
        "individual_total": 0,
        "top10_total": 49.75
      }
    }
  ]
}