{
  "secCode": "6166",
  "issuerName": "株式会社中村超硬",
  "updated_at": "2026/07/13 22:03 JST",
  "latestDate": "2026-07-01",
  "latest": [
    {
      "rank": 1,
      "name": "楽天証券株式会社",
      "shares": 340900,
      "ratio": 3.09,
      "category": "securities",
      "category_label": "証券会社",
      "is_founder_family": false
    },
    {
      "rank": 2,
      "name": "井上　誠",
      "shares": 258920,
      "ratio": 2.35,
      "category": "individual",
      "category_label": "個人（創業者一族の可能性）",
      "is_founder_family": false
    },
    {
      "rank": 3,
      "name": "株式会社ナカムラコーポレーション",
      "shares": 179000,
      "ratio": 1.62,
      "category": "corporate",
      "category_label": "事業法人",
      "is_founder_family": false
    },
    {
      "rank": 4,
      "name": "井上　紘章",
      "shares": 138800,
      "ratio": 1.26,
      "category": "individual",
      "category_label": "個人（創業者一族の可能性）",
      "is_founder_family": false
    },
    {
      "rank": 5,
      "name": "井上　絢哉",
      "shares": 133700,
      "ratio": 1.21,
      "category": "individual",
      "category_label": "個人（創業者一族の可能性）",
      "is_founder_family": false
    },
    {
      "rank": 6,
      "name": "井上　阿佐美",
      "shares": 131180,
      "ratio": 1.19,
      "category": "individual",
      "category_label": "個人（創業者一族の可能性）",
      "is_founder_family": false
    },
    {
      "rank": 7,
      "name": "PERSHING SECURITIES LTD CLIENT SAFE CUSTODY ASSET ACCOUNT（常任代理人　シティバンク、エヌ・エイ東京支店）",
      "shares": 129400,
      "ratio": 1.17,
      "category": "foreign",
      "category_label": "外国機関投資家",
      "is_founder_family": false
    },
    {
      "rank": 8,
      "name": "小山　博信",
      "shares": 104500,
      "ratio": 0.95,
      "category": "individual",
      "category_label": "個人（創業者一族の可能性）",
      "is_founder_family": false
    },
    {
      "rank": 9,
      "name": "大石　嘉昭",
      "shares": 101100,
      "ratio": 0.92,
      "category": "individual",
      "category_label": "個人（創業者一族の可能性）",
      "is_founder_family": false
    },
    {
      "rank": 10,
      "name": "株式会社SBI証券",
      "shares": 89000,
      "ratio": 0.81,
      "category": "securities",
      "category_label": "証券会社",
      "is_founder_family": false
    }
  ],
  "latestSummary": {
    "by_category": {
      "securities": 3.9,
      "individual": 7.88,
      "corporate": 1.62,
      "foreign": 1.17
    },
    "individual_total": 7.88,
    "top10_total": 14.57
  },
  "history": [
    {
      "submitDate": "2026-07-01",
      "docType": "130",
      "docTypeName": "訂正有価証券報告書－第56期(2025/04/01－2026/03/31)",
      "docID": "S100YO1L",
      "shareholders": [
        {
          "rank": 1,
          "name": "楽天証券株式会社",
          "shares": 340900,
          "ratio": 3.09,
          "category": "securities",
          "category_label": "証券会社",
          "is_founder_family": false
        },
        {
          "rank": 2,
          "name": "井上　誠",
          "shares": 258920,
          "ratio": 2.35,
          "category": "individual",
          "category_label": "個人（創業者一族の可能性）",
          "is_founder_family": false
        },
        {
          "rank": 3,
          "name": "株式会社ナカムラコーポレーション",
          "shares": 179000,
          "ratio": 1.62,
          "category": "corporate",
          "category_label": "事業法人",
          "is_founder_family": false
        },
        {
          "rank": 4,
          "name": "井上　紘章",
          "shares": 138800,
          "ratio": 1.26,
          "category": "individual",
          "category_label": "個人（創業者一族の可能性）",
          "is_founder_family": false
        },
        {
          "rank": 5,
          "name": "井上　絢哉",
          "shares": 133700,
          "ratio": 1.21,
          "category": "individual",
          "category_label": "個人（創業者一族の可能性）",
          "is_founder_family": false
        },
        {
          "rank": 6,
          "name": "井上　阿佐美",
          "shares": 131180,
          "ratio": 1.19,
          "category": "individual",
          "category_label": "個人（創業者一族の可能性）",
          "is_founder_family": false
        },
        {
          "rank": 7,
          "name": "PERSHING SECURITIES LTD CLIENT SAFE CUSTODY ASSET ACCOUNT（常任代理人　シティバンク、エヌ・エイ東京支店）",
          "shares": 129400,
          "ratio": 1.17,
          "category": "foreign",
          "category_label": "外国機関投資家",
          "is_founder_family": false
        },
        {
          "rank": 8,
          "name": "小山　博信",
          "shares": 104500,
          "ratio": 0.95,
          "category": "individual",
          "category_label": "個人（創業者一族の可能性）",
          "is_founder_family": false
        },
        {
          "rank": 9,
          "name": "大石　嘉昭",
          "shares": 101100,
          "ratio": 0.92,
          "category": "individual",
          "category_label": "個人（創業者一族の可能性）",
          "is_founder_family": false
        },
        {
          "rank": 10,
          "name": "株式会社SBI証券",
          "shares": 89000,
          "ratio": 0.81,
          "category": "securities",
          "category_label": "証券会社",
          "is_founder_family": false
        }
      ],
      "summary": {
        "by_category": {
          "securities": 3.9,
          "individual": 7.88,
          "corporate": 1.62,
          "foreign": 1.17
        },
        "individual_total": 7.88,
        "top10_total": 14.57
      }
    },
    {
      "submitDate": "2026-06-29",
      "docType": "120",
      "docTypeName": "有価証券報告書－第56期(2025/04/01－2026/03/31)",
      "docID": "S100YM8Y",
      "shareholders": [
        {
          "rank": 1,
          "name": "楽天証券株式会社",
          "shares": 340900,
          "ratio": 3.09,
          "category": "securities",
          "category_label": "証券会社",
          "is_founder_family": false
        },
        {
          "rank": 2,
          "name": "井上　誠",
          "shares": 258920,
          "ratio": 2.35,
          "category": "individual",
          "category_label": "個人（創業者一族の可能性）",
          "is_founder_family": false
        },
        {
          "rank": 3,
          "name": "株式会社ナカムラコーポレーション",
          "shares": 179000,
          "ratio": 1.62,
          "category": "corporate",
          "category_label": "事業法人",
          "is_founder_family": false
        },
        {
          "rank": 4,
          "name": "井上　紘章",
          "shares": 138800,
          "ratio": 1.26,
          "category": "individual",
          "category_label": "個人（創業者一族の可能性）",
          "is_founder_family": false
        },
        {
          "rank": 5,
          "name": "井上　絢哉",
          "shares": 133700,
          "ratio": 1.21,
          "category": "individual",
          "category_label": "個人（創業者一族の可能性）",
          "is_founder_family": false
        },
        {
          "rank": 6,
          "name": "井上　阿佐美",
          "shares": 131180,
          "ratio": 1.19,
          "category": "individual",
          "category_label": "個人（創業者一族の可能性）",
          "is_founder_family": false
        },
        {
          "rank": 7,
          "name": "PERSHING SECURITIES LTD CLIENT SAFE CUSTODY ASSET ACCOUNT（常任代理人　シティバンク、エヌ・エイ東京支店）",
          "shares": 129400,
          "ratio": 1.17,
          "category": "foreign",
          "category_label": "外国機関投資家",
          "is_founder_family": false
        },
        {
          "rank": 8,
          "name": "小山　博信",
          "shares": 104500,
          "ratio": 0.95,
          "category": "individual",
          "category_label": "個人（創業者一族の可能性）",
          "is_founder_family": false
        },
        {
          "rank": 9,
          "name": "大石　嘉昭",
          "shares": 101100,
          "ratio": 0.92,
          "category": "individual",
          "category_label": "個人（創業者一族の可能性）",
          "is_founder_family": false
        },
        {
          "rank": 10,
          "name": "株式会社SBI証券",
          "shares": 89000,
          "ratio": 0.81,
          "category": "securities",
          "category_label": "証券会社",
          "is_founder_family": false
        }
      ],
      "summary": {
        "by_category": {
          "securities": 3.9,
          "individual": 7.88,
          "corporate": 1.62,
          "foreign": 1.17
        },
        "individual_total": 7.88,
        "top10_total": 14.57
      }
    }
  ]
}