{
  "secCode": "9008",
  "issuerName": "京王電鉄株式会社",
  "updated_at": "2026/07/04 18:33 JST",
  "latestDate": "2026-06-23",
  "latest": [
    {
      "rank": 1,
      "name": "日本マスタートラスト信託銀行株式会社（信託口）",
      "shares": 15051000,
      "ratio": 12.99,
      "category": "trust",
      "category_label": "信託口（国内機関・年金/投信）",
      "is_founder_family": false
    },
    {
      "rank": 2,
      "name": "日本生命保険相互会社",
      "shares": 6018000,
      "ratio": 5.19,
      "category": "financial",
      "category_label": "銀行・保険",
      "is_founder_family": false
    },
    {
      "rank": 3,
      "name": "株式会社日本カストディ銀行（信託口）",
      "shares": 5238000,
      "ratio": 4.52,
      "category": "trust",
      "category_label": "信託口（国内機関・年金/投信）",
      "is_founder_family": false
    },
    {
      "rank": 4,
      "name": "太陽生命保険株式会社",
      "shares": 4500000,
      "ratio": 3.88,
      "category": "financial",
      "category_label": "銀行・保険",
      "is_founder_family": false
    },
    {
      "rank": 5,
      "name": "株式会社日本カストディ銀行（三井住友信託銀行退職給付信託口）",
      "shares": 2000000,
      "ratio": 1.73,
      "category": "trust",
      "category_label": "信託口（国内機関・年金/投信）",
      "is_founder_family": false
    },
    {
      "rank": 6,
      "name": "三井住友信託銀行株式会社",
      "shares": 2000000,
      "ratio": 1.73,
      "category": "financial",
      "category_label": "銀行・保険",
      "is_founder_family": false
    },
    {
      "rank": 7,
      "name": "富国生命保険相互会社",
      "shares": 1918000,
      "ratio": 1.66,
      "category": "financial",
      "category_label": "銀行・保険",
      "is_founder_family": false
    },
    {
      "rank": 8,
      "name": "JP MORGAN CHASE BANK 385781（常任代理人 株式会社みずほ銀行）",
      "shares": 1591000,
      "ratio": 1.37,
      "category": "foreign",
      "category_label": "外国機関投資家",
      "is_founder_family": false
    },
    {
      "rank": 9,
      "name": "株式会社京王閣",
      "shares": 1454000,
      "ratio": 1.26,
      "category": "corporate",
      "category_label": "事業法人",
      "is_founder_family": false
    },
    {
      "rank": 10,
      "name": "STATE STREET BANK AND TRUST COMPANY 505001（常任代理人 株式会社みずほ銀行）",
      "shares": 1444000,
      "ratio": 1.25,
      "category": "foreign",
      "category_label": "外国機関投資家",
      "is_founder_family": false
    }
  ],
  "latestSummary": {
    "by_category": {
      "trust": 19.24,
      "financial": 12.46,
      "foreign": 2.62,
      "corporate": 1.26
    },
    "individual_total": 0,
    "top10_total": 35.58
  },
  "history": [
    {
      "submitDate": "2026-06-23",
      "docType": "120",
      "docTypeName": "有価証券報告書－第105期(2025/04/01－2026/03/31)",
      "docID": "S100YF0G",
      "shareholders": [
        {
          "rank": 1,
          "name": "日本マスタートラスト信託銀行株式会社（信託口）",
          "shares": 15051000,
          "ratio": 12.99,
          "category": "trust",
          "category_label": "信託口（国内機関・年金/投信）",
          "is_founder_family": false
        },
        {
          "rank": 2,
          "name": "日本生命保険相互会社",
          "shares": 6018000,
          "ratio": 5.19,
          "category": "financial",
          "category_label": "銀行・保険",
          "is_founder_family": false
        },
        {
          "rank": 3,
          "name": "株式会社日本カストディ銀行（信託口）",
          "shares": 5238000,
          "ratio": 4.52,
          "category": "trust",
          "category_label": "信託口（国内機関・年金/投信）",
          "is_founder_family": false
        },
        {
          "rank": 4,
          "name": "太陽生命保険株式会社",
          "shares": 4500000,
          "ratio": 3.88,
          "category": "financial",
          "category_label": "銀行・保険",
          "is_founder_family": false
        },
        {
          "rank": 5,
          "name": "株式会社日本カストディ銀行（三井住友信託銀行退職給付信託口）",
          "shares": 2000000,
          "ratio": 1.73,
          "category": "trust",
          "category_label": "信託口（国内機関・年金/投信）",
          "is_founder_family": false
        },
        {
          "rank": 6,
          "name": "三井住友信託銀行株式会社",
          "shares": 2000000,
          "ratio": 1.73,
          "category": "financial",
          "category_label": "銀行・保険",
          "is_founder_family": false
        },
        {
          "rank": 7,
          "name": "富国生命保険相互会社",
          "shares": 1918000,
          "ratio": 1.66,
          "category": "financial",
          "category_label": "銀行・保険",
          "is_founder_family": false
        },
        {
          "rank": 8,
          "name": "JP MORGAN CHASE BANK 385781（常任代理人 株式会社みずほ銀行）",
          "shares": 1591000,
          "ratio": 1.37,
          "category": "foreign",
          "category_label": "外国機関投資家",
          "is_founder_family": false
        },
        {
          "rank": 9,
          "name": "株式会社京王閣",
          "shares": 1454000,
          "ratio": 1.26,
          "category": "corporate",
          "category_label": "事業法人",
          "is_founder_family": false
        },
        {
          "rank": 10,
          "name": "STATE STREET BANK AND TRUST COMPANY 505001（常任代理人 株式会社みずほ銀行）",
          "shares": 1444000,
          "ratio": 1.25,
          "category": "foreign",
          "category_label": "外国機関投資家",
          "is_founder_family": false
        }
      ],
      "summary": {
        "by_category": {
          "trust": 19.24,
          "financial": 12.46,
          "foreign": 2.62,
          "corporate": 1.26
        },
        "individual_total": 0,
        "top10_total": 35.58
      }
    }
  ]
}